lab11_32bit_Multiplier/part1/32mpy.v
`timescale 1ns/1ps
module lab(CLK, RST, in_a, in_b, Product, Product_Valid);
input CLK, RST;
input [31:0]	in_a;// Multiplicand
input [31:0]	in_b;// Multiplier
output reg [63:0] Product;
output reg Product_Valid;

reg [63:0] Mplicand;
reg [31:0] Mplier;
reg [6:0]	Counter ;
reg	sign;

//Counter
always @(posedge CLK or posedge RST)
begin
	if(RST)
		Counter <=6'b0;
	else
		Counter <= Counter +6'b1;
end

//Multiplier
always @(posedge CLK or posedge RST)
begin
	//初始化數值
	if(RST) begin
		Product  <= 64'b0;
		Mplicand <= 64'b0;
		Mplier   <= 32'b0;	
	end 
	
	//輸入乘數與被乘數
	else if(Counter == 6'd0) begin
		Mplicand <= {32'b0,in_a};
		Mplier <= in_b;
	end 
	
	//乘法與數值移位
	/* write down your design below */
	else if(Counter <=6'd32) 
	begin
		if(Mplier[0] == 1'b1)	
			Product <= Mplicand + Product;
		Mplicand <= Mplicand << 1'b1;
		Mplier <= Mplier >> 1'b1;
	end 
	/* write down your design upon */
end

//判斷輸出
always @(posedge CLK or posedge RST)
begin
	if(RST)
		Product_Valid <=1'b0;
	else if(Counter==6'd32)
		Product_Valid <=1'b1;
	else
		Product_Valid <=1'b0;
end

endmodule

lab11_32bit_Multiplier/part5/tb32mpy.v
`timescale 1ns/1ps
`include "32mpy.v"

module tb_lab();
reg [31:0] in_a;
reg [31:0] in_b;
reg CLK;
reg reset;
wire signed [63:0] out;
wire out_valid;

reg [5:0]	count;
reg signed [64:0]	correct_ans;
reg error;
reg signed [63:0]	 temp_a;
reg signed [63:0]	temp_b;

lab m1(CLK, reset, in_a, in_b, out, out_valid);

initial begin
	$dumpfile("lab11.vcd");  //gtkwave
	$dumpvars;
	CLK = 1'b0;
	
	#10 reset = 1;//正數*正數
	temp_a = 32'd30;
	temp_b = 32'd90;
	#20 reset = 0;
	
	#260 reset = 1;//正數*負數
	temp_a = 32'd30;
	temp_b = -32'd90;
	#20 reset = 0;
	
	#260 reset = 1;//負數*正數
	temp_a = -32'd30;
	temp_b = 32'd90;
	#20 reset = 0;
	
	#260 reset = 1;//負數*負數
	temp_a = -32'd30;
	temp_b = 32'd1;
	#20 reset = 0;

	#260 $finish;
end

always #10 CLK = ~CLK;

always @(posedge CLK or posedge reset)
begin
	if(reset)//初始化
	begin
		count <= 0;
		in_a <= temp_a;
		in_b <= temp_b;
		correct_ans <= 0;
		error <= 0;
	end

	else//對答案
	begin
		correct_ans <= temp_a *temp_b;
		count <= count +1;

		if(out_valid==1)
			if(out != correct_ans)
			begin
				error <=1;
				$display ();
				$display ("// Fail //");
				$display ("//%d * %d = ?",temp_a, temp_b);
				$display ("//your answer is %d, but correct answer is %d\n",
				out, correct_ans);
			end
			
			else
			begin
				error <= 0;
				$display ();
				$display ("// Successful //");
				$display ("//%d * %d = ?",temp_a, temp_b);
				$display ("//your answer is %d,  correct answer is %d\n",
				out, correct_ans);
			end
	end
end

endmodule

lab11_32bit_Multiplier/part1/lab11.vcd
$date
	Mon May 28 20:30:34 2018
$end
$version
	Icarus Verilog
$end
$timescale
	1ps
$end
$scope module tb_lab $end
$var wire 1 ! out_valid $end
$var wire 64 " out [63:0] $end
$var reg 1 # CLK $end
$var reg 65 $ correct_ans [64:0] $end
$var reg 6 % count [5:0] $end
$var reg 1 & error $end
$var reg 32 ' in_a [31:0] $end
$var reg 32 ( in_b [31:0] $end
$var reg 1 ) reset $end
$var reg 64 * temp_a [63:0] $end
$var reg 64 + temp_b [63:0] $end
$scope module m1 $end
$var wire 1 # CLK $end
$var wire 1 ) RST $end
$var wire 32 , in_a [31:0] $end
$var wire 32 - in_b [31:0] $end
$var reg 7 . Counter [6:0] $end
$var reg 64 / Mplicand [63:0] $end
$var reg 32 0 Mplier [31:0] $end
$var reg 64 1 Product [63:0] $end
$var reg 1 ! Product_Valid $end
$upscope $end
$upscope $end
$enddefinitions $end
#0
$dumpvars
bx 1
bx 0
bx /
bx .
bx -
bx ,
bx +
bx *
x)
bx (
bx '
x&
bx %
bx $
0#
bx "
x!
$end
#10000
b0 .
b0 0
b0 /
b0 "
b0 1
0!
0&
b0 $
b1011010 (
b1011010 -
b11110 '
b11110 ,
b0 %
1#
b1011010 +
b11110 *
1)
#20000
0#
#30000
b1 %
b101010001100 $
b1011010 0
b11110 /
b1 .
1#
0)
#40000
0#
#50000
b10 .
b101101 0
b111100 /
b10 %
1#
#60000
0#
#70000
b11 %
b10110 0
b1111000 /
b111100 "
b111100 1
b11 .
1#
#80000
0#
#90000
b100 .
b1011 0
b11110000 /
b100 %
1#
#100000
0#
#110000
b101 %
b101 0
b111100000 /
b100101100 "
b100101100 1
b101 .
1#
#120000
0#
#130000
b110 .
b10 0
b1111000000 /
b1100001100 "
b1100001100 1
b110 %
1#
#140000
0#
#150000
b111 %
b1 0
b11110000000 /
b111 .
1#
#160000
0#
#170000
b1000 .
b0 0
b111100000000 /
b101010001100 "
b101010001100 1
b1000 %
1#
#180000
0#
#190000
b1001 %
b1111000000000 /
b1001 .
1#
#200000
0#
#210000
b1010 .
b11110000000000 /
b1010 %
1#
#220000
0#
#230000
b1011 %
b111100000000000 /
b1011 .
1#
#240000
0#
#250000
b1100 .
b1111000000000000 /
b1100 %
1#
#260000
0#
#270000
b1101 %
b11110000000000000 /
b1101 .
1#
#280000
0#
#290000
b1110 .
b111100000000000000 /
b1110 %
1#
#300000
0#
#310000
b1111 %
b1111000000000000000 /
b1111 .
1#
#320000
0#
#330000
b10000 .
b11110000000000000000 /
b10000 %
1#
#340000
0#
#350000
b10001 %
b111100000000000000000 /
b10001 .
1#
#360000
0#
#370000
b10010 .
b1111000000000000000000 /
b10010 %
1#
#380000
0#
#390000
b10011 %
b11110000000000000000000 /
b10011 .
1#
#400000
0#
#410000
b10100 .
b111100000000000000000000 /
b10100 %
1#
#420000
0#
#430000
b10101 %
b1111000000000000000000000 /
b10101 .
1#
#440000
0#
#450000
b10110 .
b11110000000000000000000000 /
b10110 %
1#
#460000
0#
#470000
b10111 %
b111100000000000000000000000 /
b10111 .
1#
#480000
0#
#490000
b11000 .
b1111000000000000000000000000 /
b11000 %
1#
#500000
0#
#510000
b11001 %
b11110000000000000000000000000 /
b11001 .
1#
#520000
0#
#530000
b11010 .
b111100000000000000000000000000 /
b11010 %
1#
#540000
0#
#550000
b11011 %
b1111000000000000000000000000000 /
b11011 .
1#
#560000
0#
#570000
b11100 .
b11110000000000000000000000000000 /
b11100 %
1#
#580000
0#
#590000
b11101 %
b111100000000000000000000000000000 /
b11101 .
1#
#600000
0#
#610000
b11110 .
b1111000000000000000000000000000000 /
b11110 %
1#
#620000
0#
#630000
b11111 %
b11110000000000000000000000000000000 /
b11111 .
1#
#640000
0#
#650000
b100000 .
b111100000000000000000000000000000000 /
b100000 %
1#
#660000
0#
#670000
b100001 %
1!
b1111000000000000000000000000000000000 /
b100001 .
1#
#680000
0#
#690000
b100010 .
0!
b100010 %
1#
#700000
0#
#710000
b0 $
b11111111111111111111111110100110 (
b11111111111111111111111110100110 -
b0 %
b0 /
b0 "
b0 1
b0 .
1#
b1111111111111111111111111111111111111111111111111111111110100110 +
1)
#720000
0#
#730000
b1 .
b11111111111111111111111110100110 0
b11110 /
b1 %
b11111111111111111111111111111111111111111111111111111010101110100 $
1#
0)
#740000
0#
#750000
b10 %
b1111111111111111111111111010011 0
b111100 /
b10 .
1#
#760000
0#
#770000
b11 .
b111111111111111111111111101001 0
b1111000 /
b111100 "
b111100 1
b11 %
1#
#780000
0#
#790000
b100 %
b11111111111111111111111110100 0
b11110000 /
b10110100 "
b10110100 1
b100 .
1#
#800000
0#
#810000
b101 .
b1111111111111111111111111010 0
b111100000 /
b101 %
1#
#820000
0#
#830000
b110 %
b111111111111111111111111101 0
b1111000000 /
b110 .
1#
#840000
0#
#850000
b111 .
b11111111111111111111111110 0
b11110000000 /
b10001110100 "
b10001110100 1
b111 %
1#
#860000
0#
#870000
b1000 %
b1111111111111111111111111 0
b111100000000 /
b1000 .
1#
#880000
0#
#890000
b1001 .
b111111111111111111111111 0
b1111000000000 /
b1001101110100 "
b1001101110100 1
b1001 %
1#
#900000
0#
#910000
b1010 %
b11111111111111111111111 0
b11110000000000 /
b11000101110100 "
b11000101110100 1
b1010 .
1#
#920000
0#
#930000
b1011 .
b1111111111111111111111 0
b111100000000000 /
b110110101110100 "
b110110101110100 1
b1011 %
1#
#940000
0#
#950000
b1100 %
b111111111111111111111 0
b1111000000000000 /
b1110010101110100 "
b1110010101110100 1
b1100 .
1#
#960000
0#
#970000
b1101 .
b11111111111111111111 0
b11110000000000000 /
b11101010101110100 "
b11101010101110100 1
b1101 %
1#
#980000
0#
#990000
b1110 %
b1111111111111111111 0
b111100000000000000 /
b111011010101110100 "
b111011010101110100 1
b1110 .
1#
#1000000
0#
#1010000
b1111 .
b111111111111111111 0
b1111000000000000000 /
b1110111010101110100 "
b1110111010101110100 1
b1111 %
1#
#1020000
0#
#1030000
b10000 %
b11111111111111111 0
b11110000000000000000 /
b11101111010101110100 "
b11101111010101110100 1
b10000 .
1#
#1040000
0#
#1050000
b10001 .
b1111111111111111 0
b111100000000000000000 /
b111011111010101110100 "
b111011111010101110100 1
b10001 %
1#
#1060000
0#
#1070000
b10010 %
b111111111111111 0
b1111000000000000000000 /
b1110111111010101110100 "
b1110111111010101110100 1
b10010 .
1#
#1080000
0#
#1090000
b10011 .
b11111111111111 0
b11110000000000000000000 /
b11101111111010101110100 "
b11101111111010101110100 1
b10011 %
1#
#1100000
0#
#1110000
b10100 %
b1111111111111 0
b111100000000000000000000 /
b111011111111010101110100 "
b111011111111010101110100 1
b10100 .
1#
#1120000
0#
#1130000
b10101 .
b111111111111 0
b1111000000000000000000000 /
b1110111111111010101110100 "
b1110111111111010101110100 1
b10101 %
1#
#1140000
0#
#1150000
b10110 %
b11111111111 0
b11110000000000000000000000 /
b11101111111111010101110100 "
b11101111111111010101110100 1
b10110 .
1#
#1160000
0#
#1170000
b10111 .
b1111111111 0
b111100000000000000000000000 /
b111011111111111010101110100 "
b111011111111111010101110100 1
b10111 %
1#
#1180000
0#
#1190000
b11000 %
b111111111 0
b1111000000000000000000000000 /
b1110111111111111010101110100 "
b1110111111111111010101110100 1
b11000 .
1#
#1200000
0#
#1210000
b11001 .
b11111111 0
b11110000000000000000000000000 /
b11101111111111111010101110100 "
b11101111111111111010101110100 1
b11001 %
1#
#1220000
0#
#1230000
b11010 %
b1111111 0
b111100000000000000000000000000 /
b111011111111111111010101110100 "
b111011111111111111010101110100 1
b11010 .
1#
#1240000
0#
#1250000
b11011 .
b111111 0
b1111000000000000000000000000000 /
b1110111111111111111010101110100 "
b1110111111111111111010101110100 1
b11011 %
1#
#1260000
0#
#1270000
b11100 %
b11111 0
b11110000000000000000000000000000 /
b11101111111111111111010101110100 "
b11101111111111111111010101110100 1
b11100 .
1#
#1280000
0#
#1290000
b11101 .
b1111 0
b111100000000000000000000000000000 /
b111011111111111111111010101110100 "
b111011111111111111111010101110100 1
b11101 %
1#
#1300000
0#
#1310000
b11110 %
b111 0
b1111000000000000000000000000000000 /
b1110111111111111111111010101110100 "
b1110111111111111111111010101110100 1
b11110 .
1#
#1320000
0#
#1330000
b11111 .
b11 0
b11110000000000000000000000000000000 /
b11101111111111111111111010101110100 "
b11101111111111111111111010101110100 1
b11111 %
1#
#1340000
0#
#1350000
b100000 %
b1 0
b111100000000000000000000000000000000 /
b111011111111111111111111010101110100 "
b111011111111111111111111010101110100 1
b100000 .
1#
#1360000
0#
#1370000
b100001 .
b0 0
b1111000000000000000000000000000000000 /
b1110111111111111111111111010101110100 "
b1110111111111111111111111010101110100 1
1!
b100001 %
1#
#1380000
0#
#1390000
1&
b100010 %
0!
b100010 .
1#
#1400000
0#
#1410000
b0 .
b0 /
b0 "
b0 1
0&
b0 $
b1011010 (
b1011010 -
b11111111111111111111111111100010 '
b11111111111111111111111111100010 ,
b0 %
1#
b1011010 +
b1111111111111111111111111111111111111111111111111111111111100010 *
1)
#1420000
0#
#1430000
b1 %
b11111111111111111111111111111111111111111111111111111010101110100 $
b1011010 0
b11111111111111111111111111100010 /
b1 .
1#
0)
#1440000
0#
#1450000
b10 .
b101101 0
b111111111111111111111111111000100 /
b10 %
1#
#1460000
0#
#1470000
b11 %
b10110 0
b1111111111111111111111111110001000 /
b111111111111111111111111111000100 "
b111111111111111111111111111000100 1
b11 .
1#
#1480000
0#
#1490000
b100 .
b1011 0
b11111111111111111111111111100010000 /
b100 %
1#
#1500000
0#
#1510000
b101 %
b101 0
b111111111111111111111111111000100000 /
b100111111111111111111111111011010100 "
b100111111111111111111111111011010100 1
b101 .
1#
#1520000
0#
#1530000
b110 .
b10 0
b1111111111111111111111111110001000000 /
b1100111111111111111111111110011110100 "
b1100111111111111111111111110011110100 1
b110 %
1#
#1540000
0#
#1550000
b111 %
b1 0
b11111111111111111111111111100010000000 /
b111 .
1#
#1560000
0#
#1570000
b1000 .
b0 0
b111111111111111111111111111000100000000 /
b101100111111111111111111111010101110100 "
b101100111111111111111111111010101110100 1
b1000 %
1#
#1580000
0#
#1590000
b1001 %
b1111111111111111111111111110001000000000 /
b1001 .
1#
#1600000
0#
#1610000
b1010 .
b11111111111111111111111111100010000000000 /
b1010 %
1#
#1620000
0#
#1630000
b1011 %
b111111111111111111111111111000100000000000 /
b1011 .
1#
#1640000
0#
#1650000
b1100 .
b1111111111111111111111111110001000000000000 /
b1100 %
1#
#1660000
0#
#1670000
b1101 %
b11111111111111111111111111100010000000000000 /
b1101 .
1#
#1680000
0#
#1690000
b1110 .
b111111111111111111111111111000100000000000000 /
b1110 %
1#
#1700000
0#
#1710000
b1111 %
b1111111111111111111111111110001000000000000000 /
b1111 .
1#
#1720000
0#
#1730000
b10000 .
b11111111111111111111111111100010000000000000000 /
b10000 %
1#
#1740000
0#
#1750000
b10001 %
b111111111111111111111111111000100000000000000000 /
b10001 .
1#
#1760000
0#
#1770000
b10010 .
b1111111111111111111111111110001000000000000000000 /
b10010 %
1#
#1780000
0#
#1790000
b10011 %
b11111111111111111111111111100010000000000000000000 /
b10011 .
1#
#1800000
0#
#1810000
b10100 .
b111111111111111111111111111000100000000000000000000 /
b10100 %
1#
#1820000
0#
#1830000
b10101 %
b1111111111111111111111111110001000000000000000000000 /
b10101 .
1#
#1840000
0#
#1850000
b10110 .
b11111111111111111111111111100010000000000000000000000 /
b10110 %
1#
#1860000
0#
#1870000
b10111 %
b111111111111111111111111111000100000000000000000000000 /
b10111 .
1#
#1880000
0#
#1890000
b11000 .
b1111111111111111111111111110001000000000000000000000000 /
b11000 %
1#
#1900000
0#
#1910000
b11001 %
b11111111111111111111111111100010000000000000000000000000 /
b11001 .
1#
#1920000
0#
#1930000
b11010 .
b111111111111111111111111111000100000000000000000000000000 /
b11010 %
1#
#1940000
0#
#1950000
b11011 %
b1111111111111111111111111110001000000000000000000000000000 /
b11011 .
1#
#1960000
0#
#1970000
b11100 .
b11111111111111111111111111100010000000000000000000000000000 /
b11100 %
1#
#1980000
0#
#1990000
b11101 %
b111111111111111111111111111000100000000000000000000000000000 /
b11101 .
1#
#2000000
0#
#2010000
b11110 .
b1111111111111111111111111110001000000000000000000000000000000 /
b11110 %
1#
#2020000
0#
#2030000
b11111 %
b11111111111111111111111111100010000000000000000000000000000000 /
b11111 .
1#
#2040000
0#
#2050000
b100000 .
b111111111111111111111111111000100000000000000000000000000000000 /
b100000 %
1#
#2060000
0#
#2070000
b100001 %
1!
b1111111111111111111111111110001000000000000000000000000000000000 /
b100001 .
1#
#2080000
0#
#2090000
b100010 .
0!
1&
b100010 %
1#
#2100000
0#
#2110000
0&
b0 $
b11111111111111111111111110100110 (
b11111111111111111111111110100110 -
b0 %
b0 /
b0 "
b0 1
b0 .
1#
b1111111111111111111111111111111111111111111111111111111110100110 +
1)
#2120000
0#
#2130000
b1 .
b11111111111111111111111110100110 0
b11111111111111111111111111100010 /
b1 %
b101010001100 $
1#
0)
#2140000
0#
#2150000
b10 %
b1111111111111111111111111010011 0
b111111111111111111111111111000100 /
b10 .
1#
#2160000
0#
#2170000
b11 .
b111111111111111111111111101001 0
b1111111111111111111111111110001000 /
b111111111111111111111111111000100 "
b111111111111111111111111111000100 1
b11 %
1#
#2180000
0#
#2190000
b100 %
b11111111111111111111111110100 0
b11111111111111111111111111100010000 /
b10111111111111111111111111101001100 "
b10111111111111111111111111101001100 1
b100 .
1#
#2200000
0#
#2210000
b101 .
b1111111111111111111111111010 0
b111111111111111111111111111000100000 /
b101 %
1#
#2220000
0#
#2230000
b110 %
b111111111111111111111111101 0
b1111111111111111111111111110001000000 /
b110 .
1#
#2240000
0#
#2250000
b111 .
b11111111111111111111111110 0
b11111111111111111111111111100010000000 /
b10010111111111111111111111101110001100 "
b10010111111111111111111111101110001100 1
b111 %
1#
#2260000
0#
#2270000
b1000 %
b1111111111111111111111111 0
b111111111111111111111111111000100000000 /
b1000 .
1#
#2280000
0#
#2290000
b1001 .
b111111111111111111111111 0
b1111111111111111111111111110001000000000 /
b1010010111111111111111111110110010001100 "
b1010010111111111111111111110110010001100 1
b1001 %
1#
#2300000
0#
#2310000
b1010 %
b11111111111111111111111 0
b11111111111111111111111111100010000000000 /
b11010010111111111111111111100111010001100 "
b11010010111111111111111111100111010001100 1
b1010 .
1#
#2320000
0#
#2330000
b1011 .
b1111111111111111111111 0
b111111111111111111111111111000100000000000 /
b111010010111111111111111111001001010001100 "
b111010010111111111111111111001001010001100 1
b1011 %
1#
#2340000
0#
#2350000
b1100 %
b111111111111111111111 0
b1111111111111111111111111110001000000000000 /
b1111010010111111111111111110001101010001100 "
b1111010010111111111111111110001101010001100 1
b1100 .
1#
#2360000
0#
#2370000
b1101 .
b11111111111111111111 0
b11111111111111111111111111100010000000000000 /
b11111010010111111111111111100010101010001100 "
b11111010010111111111111111100010101010001100 1
b1101 %
1#
#2380000
0#
#2390000
b1110 %
b1111111111111111111 0
b111111111111111111111111111000100000000000000 /
b111111010010111111111111111000100101010001100 "
b111111010010111111111111111000100101010001100 1
b1110 .
1#
#2400000
0#
#2410000
b1111 .
b111111111111111111 0
b1111111111111111111111111110001000000000000000 /
b1111111010010111111111111110001000101010001100 "
b1111111010010111111111111110001000101010001100 1
b1111 %
1#
#2420000
0#
#2430000
b10000 %
b11111111111111111 0
b11111111111111111111111111100010000000000000000 /
b11111111010010111111111111100010000101010001100 "
b11111111010010111111111111100010000101010001100 1
b10000 .
1#
#2440000
0#
#2450000
b10001 .
b1111111111111111 0
b111111111111111111111111111000100000000000000000 /
b111111111010010111111111111000100000101010001100 "
b111111111010010111111111111000100000101010001100 1
b10001 %
1#
#2460000
0#
#2470000
b10010 %
b111111111111111 0
b1111111111111111111111111110001000000000000000000 /
b1111111111010010111111111110001000000101010001100 "
b1111111111010010111111111110001000000101010001100 1
b10010 .
1#
#2480000
0#
#2490000
b10011 .
b11111111111111 0
b11111111111111111111111111100010000000000000000000 /
b11111111111010010111111111100010000000101010001100 "
b11111111111010010111111111100010000000101010001100 1
b10011 %
1#
#2500000
0#
#2510000
b10100 %
b1111111111111 0
b111111111111111111111111111000100000000000000000000 /
b111111111111010010111111111000100000000101010001100 "
b111111111111010010111111111000100000000101010001100 1
b10100 .
1#
#2520000
0#
#2530000
b10101 .
b111111111111 0
b1111111111111111111111111110001000000000000000000000 /
b1111111111111010010111111110001000000000101010001100 "
b1111111111111010010111111110001000000000101010001100 1
b10101 %
1#
#2540000
0#
#2550000
b10110 %
b11111111111 0
b11111111111111111111111111100010000000000000000000000 /
b11111111111111010010111111100010000000000101010001100 "
b11111111111111010010111111100010000000000101010001100 1
b10110 .
1#
#2560000
0#
#2570000
b10111 .
b1111111111 0
b111111111111111111111111111000100000000000000000000000 /
b111111111111111010010111111000100000000000101010001100 "
b111111111111111010010111111000100000000000101010001100 1
b10111 %
1#
#2580000
0#
#2590000
b11000 %
b111111111 0
b1111111111111111111111111110001000000000000000000000000 /
b1111111111111111010010111110001000000000000101010001100 "
b1111111111111111010010111110001000000000000101010001100 1
b11000 .
1#
#2600000
0#
#2610000
b11001 .
b11111111 0
b11111111111111111111111111100010000000000000000000000000 /
b11111111111111111010010111100010000000000000101010001100 "
b11111111111111111010010111100010000000000000101010001100 1
b11001 %
1#
#2620000
0#
#2630000
b11010 %
b1111111 0
b111111111111111111111111111000100000000000000000000000000 /
b111111111111111111010010111000100000000000000101010001100 "
b111111111111111111010010111000100000000000000101010001100 1
b11010 .
1#
#2640000
0#
#2650000
b11011 .
b111111 0
b1111111111111111111111111110001000000000000000000000000000 /
b1111111111111111111010010110001000000000000000101010001100 "
b1111111111111111111010010110001000000000000000101010001100 1
b11011 %
1#
#2660000
0#
#2670000
b11100 %
b11111 0
b11111111111111111111111111100010000000000000000000000000000 /
b11111111111111111111010010100010000000000000000101010001100 "
b11111111111111111111010010100010000000000000000101010001100 1
b11100 .
1#
#2680000
0#
#2690000
b11101 .
b1111 0
b111111111111111111111111111000100000000000000000000000000000 /
b111111111111111111111010010000100000000000000000101010001100 "
b111111111111111111111010010000100000000000000000101010001100 1
b11101 %
1#
#2700000
0#
#2710000
b11110 %
b111 0
b1111111111111111111111111110001000000000000000000000000000000 /
b1111111111111111111111010001001000000000000000000101010001100 "
b1111111111111111111111010001001000000000000000000101010001100 1
b11110 .
1#
#2720000
0#
#2730000
b11111 .
b11 0
b11111111111111111111111111100010000000000000000000000000000000 /
b11111111111111111111111001111010000000000000000000101010001100 "
b11111111111111111111111001111010000000000000000000101010001100 1
b11111 %
1#
#2740000
0#
#2750000
b100000 %
b1 0
b111111111111111111111111111000100000000000000000000000000000000 /
b111111111111111111111111001011100000000000000000000101010001100 "
b111111111111111111111111001011100000000000000000000101010001100 1
b100000 .
1#
#2760000
0#
#2770000
b100001 .
b0 0
b1111111111111111111111111110001000000000000000000000000000000000 /
b1111111111111111111111111000100000000000000000000000101010001100 "
b1111111111111111111111111000100000000000000000000000101010001100 1
1!
b100001 %
1#
#2780000
0#
#2790000
1&
b100010 %
0!
b100010 .
1#
#2800000
0#
#2810000
b0 .
b0 /
b0 "
b0 1
0&
b0 $
b11111111111111111111111111111111 (
b11111111111111111111111111111111 -
b11111111111111111111111111111111 '
b11111111111111111111111111111111 ,
b0 %
1#
b11111111111111111111111111111111 +
b11111111111111111111111111111111 *
1)
#2820000
0#
#2830000
b1 %
b1111111111111111111111111111111000000000000000000000000000000001 $
b11111111111111111111111111111111 0
b11111111111111111111111111111111 /
b1 .
1#
0)
#2840000
0#
#2850000
b10 .
b1111111111111111111111111111111 0
b111111111111111111111111111111110 /
b11111111111111111111111111111111 "
b11111111111111111111111111111111 1
b10 %
1#
#2860000
0#
#2870000
b11 %
b111111111111111111111111111111 0
b1111111111111111111111111111111100 /
b1011111111111111111111111111111101 "
b1011111111111111111111111111111101 1
b11 .
1#
#2880000
0#
#2890000
b100 .
b11111111111111111111111111111 0
b11111111111111111111111111111111000 /
b11011111111111111111111111111111001 "
b11011111111111111111111111111111001 1
b100 %
1#
#2900000
0#
#2910000
b101 %
b1111111111111111111111111111 0
b111111111111111111111111111111110000 /
b111011111111111111111111111111110001 "
b111011111111111111111111111111110001 1
b101 .
1#
#2920000
0#
#2930000
b110 .
b111111111111111111111111111 0
b1111111111111111111111111111111100000 /
b1111011111111111111111111111111100001 "
b1111011111111111111111111111111100001 1
b110 %
1#
#2940000
0#
#2950000
b111 %
b11111111111111111111111111 0
b11111111111111111111111111111111000000 /
b11111011111111111111111111111111000001 "
b11111011111111111111111111111111000001 1
b111 .
1#
#2960000
0#
#2970000
b1000 .
b1111111111111111111111111 0
b111111111111111111111111111111110000000 /
b111111011111111111111111111111110000001 "
b111111011111111111111111111111110000001 1
b1000 %
1#
#2980000
0#
#2990000
b1001 %
b111111111111111111111111 0
b1111111111111111111111111111111100000000 /
b1111111011111111111111111111111100000001 "
b1111111011111111111111111111111100000001 1
b1001 .
1#
#3000000
0#
#3010000
b1010 .
b11111111111111111111111 0
b11111111111111111111111111111111000000000 /
b11111111011111111111111111111111000000001 "
b11111111011111111111111111111111000000001 1
b1010 %
1#
#3020000
0#
#3030000
b1011 %
b1111111111111111111111 0
b111111111111111111111111111111110000000000 /
b111111111011111111111111111111110000000001 "
b111111111011111111111111111111110000000001 1
b1011 .
1#
#3040000
0#
#3050000
b1100 .
b111111111111111111111 0
b1111111111111111111111111111111100000000000 /
b1111111111011111111111111111111100000000001 "
b1111111111011111111111111111111100000000001 1
b1100 %
1#
#3060000
0#
#3070000
b1101 %
b11111111111111111111 0
b11111111111111111111111111111111000000000000 /
b11111111111011111111111111111111000000000001 "
b11111111111011111111111111111111000000000001 1
b1101 .
1#
#3080000
0#
#3090000
b1110 .
b1111111111111111111 0
b111111111111111111111111111111110000000000000 /
b111111111111011111111111111111110000000000001 "
b111111111111011111111111111111110000000000001 1
b1110 %
1#
#3100000
0#
#3110000
b1111 %
b111111111111111111 0
b1111111111111111111111111111111100000000000000 /
b1111111111111011111111111111111100000000000001 "
b1111111111111011111111111111111100000000000001 1
b1111 .
1#
#3120000
0#
#3130000
b10000 .
b11111111111111111 0
b11111111111111111111111111111111000000000000000 /
b11111111111111011111111111111111000000000000001 "
b11111111111111011111111111111111000000000000001 1
b10000 %
1#
#3140000
0#
#3150000
b10001 %
b1111111111111111 0
b111111111111111111111111111111110000000000000000 /
b111111111111111011111111111111110000000000000001 "
b111111111111111011111111111111110000000000000001 1
b10001 .
1#
#3160000
0#
#3170000
b10010 .
b111111111111111 0
b1111111111111111111111111111111100000000000000000 /
b1111111111111111011111111111111100000000000000001 "
b1111111111111111011111111111111100000000000000001 1
b10010 %
1#
#3180000
0#
#3190000
b10011 %
b11111111111111 0
b11111111111111111111111111111111000000000000000000 /
b11111111111111111011111111111111000000000000000001 "
b11111111111111111011111111111111000000000000000001 1
b10011 .
1#
#3200000
0#
#3210000
b10100 .
b1111111111111 0
b111111111111111111111111111111110000000000000000000 /
b111111111111111111011111111111110000000000000000001 "
b111111111111111111011111111111110000000000000000001 1
b10100 %
1#
#3220000
0#
#3230000
b10101 %
b111111111111 0
b1111111111111111111111111111111100000000000000000000 /
b1111111111111111111011111111111100000000000000000001 "
b1111111111111111111011111111111100000000000000000001 1
b10101 .
1#
#3240000
0#
#3250000
b10110 .
b11111111111 0
b11111111111111111111111111111111000000000000000000000 /
b11111111111111111111011111111111000000000000000000001 "
b11111111111111111111011111111111000000000000000000001 1
b10110 %
1#
#3260000
0#
#3270000
b10111 %
b1111111111 0
b111111111111111111111111111111110000000000000000000000 /
b111111111111111111111011111111110000000000000000000001 "
b111111111111111111111011111111110000000000000000000001 1
b10111 .
1#
#3280000
0#
#3290000
b11000 .
b111111111 0
b1111111111111111111111111111111100000000000000000000000 /
b1111111111111111111111011111111100000000000000000000001 "
b1111111111111111111111011111111100000000000000000000001 1
b11000 %
1#
#3300000
0#
#3310000
b11001 %
b11111111 0
b11111111111111111111111111111111000000000000000000000000 /
b11111111111111111111111011111111000000000000000000000001 "
b11111111111111111111111011111111000000000000000000000001 1
b11001 .
1#
#3320000
0#
#3330000
b11010 .
b1111111 0
b111111111111111111111111111111110000000000000000000000000 /
b111111111111111111111111011111110000000000000000000000001 "
b111111111111111111111111011111110000000000000000000000001 1
b11010 %
1#
#3340000
0#
#3350000
b11011 %
b111111 0
b1111111111111111111111111111111100000000000000000000000000 /
b1111111111111111111111111011111100000000000000000000000001 "
b1111111111111111111111111011111100000000000000000000000001 1
b11011 .
1#
#3360000
0#
#3370000
b11100 .
b11111 0
b11111111111111111111111111111111000000000000000000000000000 /
b11111111111111111111111111011111000000000000000000000000001 "
b11111111111111111111111111011111000000000000000000000000001 1
b11100 %
1#
#3380000
0#
#3390000
b11101 %
b1111 0
b111111111111111111111111111111110000000000000000000000000000 /
b111111111111111111111111111011110000000000000000000000000001 "
b111111111111111111111111111011110000000000000000000000000001 1
b11101 .
1#
#3400000
0#
#3410000
b11110 .
b111 0
b1111111111111111111111111111111100000000000000000000000000000 /
b1111111111111111111111111111011100000000000000000000000000001 "
b1111111111111111111111111111011100000000000000000000000000001 1
b11110 %
1#
#3420000
0#
#3430000
b11111 %
b11 0
b11111111111111111111111111111111000000000000000000000000000000 /
b11111111111111111111111111111011000000000000000000000000000001 "
b11111111111111111111111111111011000000000000000000000000000001 1
b11111 .
1#
#3440000
0#
#3450000
b100000 .
b1 0
b111111111111111111111111111111110000000000000000000000000000000 /
b111111111111111111111111111111010000000000000000000000000000001 "
b111111111111111111111111111111010000000000000000000000000000001 1
b100000 %
1#
#3460000
0#
#3470000
b100001 %
1!
b0 0
b1111111111111111111111111111111100000000000000000000000000000000 /
b1111111111111111111111111111111000000000000000000000000000000001 "
b1111111111111111111111111111111000000000000000000000000000000001 1
b100001 .
1#
#3480000
0#
#3490000
b100010 .
0!
b100010 %
1#
#3500000
0#
#3510000
b0 $
b1 (
b1 -
b0 '
b0 ,
b0 %
b0 /
b0 "
b0 1
b0 .
1#
b1 +
b100000000000000000000000000000000 *
1)
#3520000
0#
#3530000
b1 .
b1 0
b1 %
b100000000000000000000000000000000 $
1#
0)
#3540000
0#
#3550000
b10 %
b0 0
b10 .
1#
#3560000
0#
#3570000
b11 .
b11 %
1#
#3580000
0#
#3590000
b100 %
b100 .
1#
#3600000
0#
#3610000
b101 .
b101 %
1#
#3620000
0#
#3630000
b110 %
b110 .
1#
#3640000
0#
#3650000
b111 .
b111 %
1#
#3660000
0#
#3670000
b1000 %
b1000 .
1#
#3680000
0#
#3690000
b1001 .
b1001 %
1#
#3700000
0#
#3710000
b1010 %
b1010 .
1#
#3720000
0#
#3730000
b1011 .
b1011 %
1#
#3740000
0#
#3750000
b1100 %
b1100 .
1#
