lab11_32bit_Multiplier/part2/32mpy.v
`timescale 1ns/1ps
module lab(CLK, RST, in_a, in_b, Product, Product_Valid);
input CLK, RST;
input [31:0] in_a;	// Multiplicand
input [31:0] in_b;  // Multiplier
output reg [63:0] Product;
output reg Product_Valid;

reg [31:0] Mplicand;
reg [7:0]	Counter ;
reg	sign;

//Counter
always @(posedge CLK or posedge RST)
begin
	if(RST)
		Counter <=7'b0;
	else
		Counter <= Counter +7'b1;
end

//Multiplier
always @(posedge CLK or posedge RST)
begin
	//初始化數值
	if(RST) begin
		Product  <= 64'b0;
		Mplicand <= 32'b0;
	end 
	
	//輸入乘數與被乘數
	else if(Counter == 7'd0) begin
		Mplicand <= in_a;
		Product <= {32'b0,in_b};
	end 
	
	//乘法與數值移位
	/* write down your design below */
	else if(Counter <=7'd64 && Counter%2==1) 
	begin
		if(Product[0] == 1'b1)	begin
			Product[63:32] <= Mplicand + Product[63:32];
		end
	end 

	else if(Counter <=7'd64 && Counter%2==0)
	begin
		Product <= Product >> 1'b1;
		//$display("%b",Product);
	end
	/* write down your design upon */
end

//判斷輸出
always @(posedge CLK or posedge RST)
begin
	if(RST)
		Product_Valid <=1'b0;
	else if(Counter==7'd64)
		Product_Valid <=1'b1;
	else
		Product_Valid <=1'b0;
end

endmodule

lab11_32bit_Multiplier/part2/tb32mpy.v
`timescale 1ns/1ps
`include "32mpy.v"

module tb_lab();
reg [31:0] in_a;
reg [31:0] in_b;
reg CLK;
reg reset;
wire [63:0] out;
wire out_valid;

reg [5:0]	count;
reg signed [64:0]	correct_ans;
reg error;
reg signed [63:0]	 temp_a;
reg signed [63:0]	temp_b;

lab m1(CLK, reset, in_a, in_b, out, out_valid);

initial begin
	$dumpfile("lab11.vcd");  //gtkwave
	$dumpvars;
	CLK = 1'b0;
	
	#10 reset = 1;//正數*正數
	temp_a = 32'd30;
	temp_b = 32'd90;
	#20 reset = 0;
	
	#1320 reset = 1;//正數*負數
	temp_a = 32'd30;
	temp_b = -32'd90;
	#20 reset = 0;
	
	#1320 reset = 1;//負數*正數
	temp_a = -32'd30;
	temp_b = 32'd90;
	#20 reset = 0;
	
	#1320 reset = 1;//負數*負數
	temp_a = -32'd30;
	temp_b = -32'd90;
	#20 reset = 0;

	#1320 reset = 1;//無號最大數*無號最大數
	temp_a = 64'd4294967295;
	temp_b = 64'd4294967295;
	#20 reset = 0;
	
	#1320 reset = 1;//無號溢位數*1
	temp_a = 64'd4294967296;
	temp_b = 64'd1;
	#20 reset = 0;
	
	#1320 reset = 1;//無號溢位數*1
	temp_a = 64'd4294967297;
	temp_b = 64'd1;
	#20 reset = 0;

	#1320 $finish;
end

always #10 CLK = ~CLK;

always @(posedge CLK or posedge reset)
begin
	if(reset)//初始化
	begin
		count <= 0;
		in_a <= temp_a;
		in_b <= temp_b;
		correct_ans <= 0;
		error <= 0;
	end

	else//對答案
	begin
		correct_ans <= temp_a *temp_b;
		count <= count +1;

		if(out_valid==1)
			if(out != correct_ans)
			begin
				error <=1;
				$display ();
				$display ("// Fail //");
				$display ("//%d * %d = ?",temp_a, temp_b);
				$display ("//your answer is %d, but correct answer is %d\n",
				out, correct_ans);
			end
			
			else
			begin
				error <= 0;
				$display ();
				$display ("// Successful //");
				$display ("//%d * %d = ?",temp_a, temp_b);
				$display ("//your answer is %d,  correct answer is %d\n",
				out, correct_ans);
			end
	end
end

endmodule

lab11_32bit_Multiplier/part2/lab11.vcd
$date
	Mon May 28 20:30:52 2018
$end
$version
	Icarus Verilog
$end
$timescale
	1ps
$end
$scope module tb_lab $end
$var wire 1 ! out_valid $end
$var wire 64 " out [63:0] $end
$var reg 1 # CLK $end
$var reg 65 $ correct_ans [64:0] $end
$var reg 6 % count [5:0] $end
$var reg 1 & error $end
$var reg 32 ' in_a [31:0] $end
$var reg 32 ( in_b [31:0] $end
$var reg 1 ) reset $end
$var reg 64 * temp_a [63:0] $end
$var reg 64 + temp_b [63:0] $end
$scope module m1 $end
$var wire 1 # CLK $end
$var wire 1 ) RST $end
$var wire 32 , in_a [31:0] $end
$var wire 32 - in_b [31:0] $end
$var reg 8 . Counter [7:0] $end
$var reg 32 / Mplicand [31:0] $end
$var reg 64 0 Product [63:0] $end
$var reg 1 ! Product_Valid $end
$upscope $end
$upscope $end
$enddefinitions $end
#0
$dumpvars
bx 0
bx /
bx .
bx -
bx ,
bx +
bx *
x)
bx (
bx '
x&
bx %
bx $
0#
bx "
x!
$end
#10000
b0 .
b0 /
b0 "
b0 0
0!
0&
b0 $
b1011010 (
b1011010 -
b11110 '
b11110 ,
b0 %
1#
b1011010 +
b11110 *
1)
#20000
0#
#30000
b1 %
b101010001100 $
b1011010 "
b1011010 0
b11110 /
b1 .
1#
0)
#40000
0#
#50000
b10 .
b10 %
1#
#60000
0#
#70000
b11 %
b101101 "
b101101 0
b11 .
1#
#80000
0#
#90000
b100 .
b1111000000000000000000000000000101101 "
b1111000000000000000000000000000101101 0
b100 %
1#
#100000
0#
#110000
b101 %
b111100000000000000000000000000010110 "
b111100000000000000000000000000010110 0
b101 .
1#
#120000
0#
#130000
b110 .
b110 %
1#
#140000
0#
#150000
b111 %
b11110000000000000000000000000001011 "
b11110000000000000000000000000001011 0
b111 .
1#
#160000
0#
#170000
b1000 .
b10010110000000000000000000000000001011 "
b10010110000000000000000000000000001011 0
b1000 %
1#
#180000
0#
#190000
b1001 %
b1001011000000000000000000000000000101 "
b1001011000000000000000000000000000101 0
b1001 .
1#
#200000
0#
#210000
b1010 .
b11000011000000000000000000000000000101 "
b11000011000000000000000000000000000101 0
b1010 %
1#
#220000
0#
#230000
b1011 %
b1100001100000000000000000000000000010 "
b1100001100000000000000000000000000010 0
b1011 .
1#
#240000
0#
#250000
b1100 .
b1100 %
1#
#260000
0#
#270000
b1101 %
b110000110000000000000000000000000001 "
b110000110000000000000000000000000001 0
b1101 .
1#
#280000
0#
#290000
b1110 .
b10101000110000000000000000000000000001 "
b10101000110000000000000000000000000001 0
b1110 %
1#
#300000
0#
#310000
b1111 %
b1010100011000000000000000000000000000 "
b1010100011000000000000000000000000000 0
b1111 .
1#
#320000
0#
#330000
b10000 .
b10000 %
1#
#340000
0#
#350000
b10001 %
b101010001100000000000000000000000000 "
b101010001100000000000000000000000000 0
b10001 .
1#
#360000
0#
#370000
b10010 .
b10010 %
1#
#380000
0#
#390000
b10011 %
b10101000110000000000000000000000000 "
b10101000110000000000000000000000000 0
b10011 .
1#
#400000
0#
#410000
b10100 .
b10100 %
1#
#420000
0#
#430000
b10101 %
b1010100011000000000000000000000000 "
b1010100011000000000000000000000000 0
b10101 .
1#
#440000
0#
#450000
b10110 .
b10110 %
1#
#460000
0#
#470000
b10111 %
b101010001100000000000000000000000 "
b101010001100000000000000000000000 0
b10111 .
1#
#480000
0#
#490000
b11000 .
b11000 %
1#
#500000
0#
#510000
b11001 %
b10101000110000000000000000000000 "
b10101000110000000000000000000000 0
b11001 .
1#
#520000
0#
#530000
b11010 .
b11010 %
1#
#540000
0#
#550000
b11011 %
b1010100011000000000000000000000 "
b1010100011000000000000000000000 0
b11011 .
1#
#560000
0#
#570000
b11100 .
b11100 %
1#
#580000
0#
#590000
b11101 %
b101010001100000000000000000000 "
b101010001100000000000000000000 0
b11101 .
1#
#600000
0#
#610000
b11110 .
b11110 %
1#
#620000
0#
#630000
b11111 %
b10101000110000000000000000000 "
b10101000110000000000000000000 0
b11111 .
1#
#640000
0#
#650000
b100000 .
b100000 %
1#
#660000
0#
#670000
b100001 %
b1010100011000000000000000000 "
b1010100011000000000000000000 0
b100001 .
1#
#680000
0#
#690000
b100010 .
b100010 %
1#
#700000
0#
#710000
b100011 %
b101010001100000000000000000 "
b101010001100000000000000000 0
b100011 .
1#
#720000
0#
#730000
b100100 .
b100100 %
1#
#740000
0#
#750000
b100101 %
b10101000110000000000000000 "
b10101000110000000000000000 0
b100101 .
1#
#760000
0#
#770000
b100110 .
b100110 %
1#
#780000
0#
#790000
b100111 %
b1010100011000000000000000 "
b1010100011000000000000000 0
b100111 .
1#
#800000
0#
#810000
b101000 .
b101000 %
1#
#820000
0#
#830000
b101001 %
b101010001100000000000000 "
b101010001100000000000000 0
b101001 .
1#
#840000
0#
#850000
b101010 .
b101010 %
1#
#860000
0#
#870000
b101011 %
b10101000110000000000000 "
b10101000110000000000000 0
b101011 .
1#
#880000
0#
#890000
b101100 .
b101100 %
1#
#900000
0#
#910000
b101101 %
b1010100011000000000000 "
b1010100011000000000000 0
b101101 .
1#
#920000
0#
#930000
b101110 .
b101110 %
1#
#940000
0#
#950000
b101111 %
b101010001100000000000 "
b101010001100000000000 0
b101111 .
1#
#960000
0#
#970000
b110000 .
b110000 %
1#
#980000
0#
#990000
b110001 %
b10101000110000000000 "
b10101000110000000000 0
b110001 .
1#
#1000000
0#
#1010000
b110010 .
b110010 %
1#
#1020000
0#
#1030000
b110011 %
b1010100011000000000 "
b1010100011000000000 0
b110011 .
1#
#1040000
0#
#1050000
b110100 .
b110100 %
1#
#1060000
0#
#1070000
b110101 %
b101010001100000000 "
b101010001100000000 0
b110101 .
1#
#1080000
0#
#1090000
b110110 .
b110110 %
1#
#1100000
0#
#1110000
b110111 %
b10101000110000000 "
b10101000110000000 0
b110111 .
1#
#1120000
0#
#1130000
b111000 .
b111000 %
1#
#1140000
0#
#1150000
b111001 %
b1010100011000000 "
b1010100011000000 0
b111001 .
1#
#1160000
0#
#1170000
b111010 .
b111010 %
1#
#1180000
0#
#1190000
b111011 %
b101010001100000 "
b101010001100000 0
b111011 .
1#
#1200000
0#
#1210000
b111100 .
b111100 %
1#
#1220000
0#
#1230000
b111101 %
b10101000110000 "
b10101000110000 0
b111101 .
1#
#1240000
0#
#1250000
b111110 .
b111110 %
1#
#1260000
0#
#1270000
b111111 %
b1010100011000 "
b1010100011000 0
b111111 .
1#
#1280000
0#
#1290000
b1000000 .
b0 %
1#
#1300000
0#
#1310000
b1 %
1!
b101010001100 "
b101010001100 0
b1000001 .
1#
#1320000
0#
#1330000
b1000010 .
0!
b10 %
1#
#1340000
0#
#1350000
b0 $
b11111111111111111111111110100110 (
b11111111111111111111111110100110 -
b0 %
b0 /
b0 "
b0 0
b0 .
1#
b1111111111111111111111111111111111111111111111111111111110100110 +
1)
#1360000
0#
#1370000
b1 .
b11111111111111111111111110100110 "
b11111111111111111111111110100110 0
b11110 /
b1 %
b11111111111111111111111111111111111111111111111111111010101110100 $
1#
0)
#1380000
0#
#1390000
b10 %
b10 .
1#
#1400000
0#
#1410000
b11 .
b1111111111111111111111111010011 "
b1111111111111111111111111010011 0
b11 %
1#
#1420000
0#
#1430000
b100 %
b1111001111111111111111111111111010011 "
b1111001111111111111111111111111010011 0
b100 .
1#
#1440000
0#
#1450000
b101 .
b111100111111111111111111111111101001 "
b111100111111111111111111111111101001 0
b101 %
1#
#1460000
0#
#1470000
b110 %
b10110100111111111111111111111111101001 "
b10110100111111111111111111111111101001 0
b110 .
1#
#1480000
0#
#1490000
b111 .
b1011010011111111111111111111111110100 "
b1011010011111111111111111111111110100 0
b111 %
1#
#1500000
0#
#1510000
b1000 %
b1000 .
1#
#1520000
0#
#1530000
b1001 .
b101101001111111111111111111111111010 "
b101101001111111111111111111111111010 0
b1001 %
1#
#1540000
0#
#1550000
b1010 %
b1010 .
1#
#1560000
0#
#1570000
b1011 .
b10110100111111111111111111111111101 "
b10110100111111111111111111111111101 0
b1011 %
1#
#1580000
0#
#1590000
b1100 %
b10001110100111111111111111111111111101 "
b10001110100111111111111111111111111101 0
b1100 .
1#
#1600000
0#
#1610000
b1101 .
b1000111010011111111111111111111111110 "
b1000111010011111111111111111111111110 0
b1101 %
1#
#1620000
0#
#1630000
b1110 %
b1110 .
1#
#1640000
0#
#1650000
b1111 .
b100011101001111111111111111111111111 "
b100011101001111111111111111111111111 0
b1111 %
1#
#1660000
0#
#1670000
b10000 %
b10011011101001111111111111111111111111 "
b10011011101001111111111111111111111111 0
b10000 .
1#
#1680000
0#
#1690000
b10001 .
b1001101110100111111111111111111111111 "
b1001101110100111111111111111111111111 0
b10001 %
1#
#1700000
0#
#1710000
b10010 %
b11000101110100111111111111111111111111 "
b11000101110100111111111111111111111111 0
b10010 .
1#
#1720000
0#
#1730000
b10011 .
b1100010111010011111111111111111111111 "
b1100010111010011111111111111111111111 0
b10011 %
1#
#1740000
0#
#1750000
b10100 %
b11011010111010011111111111111111111111 "
b11011010111010011111111111111111111111 0
b10100 .
1#
#1760000
0#
#1770000
b10101 .
b1101101011101001111111111111111111111 "
b1101101011101001111111111111111111111 0
b10101 %
1#
#1780000
0#
#1790000
b10110 %
b11100101011101001111111111111111111111 "
b11100101011101001111111111111111111111 0
b10110 .
1#
#1800000
0#
#1810000
b10111 .
b1110010101110100111111111111111111111 "
b1110010101110100111111111111111111111 0
b10111 %
1#
#1820000
0#
#1830000
b11000 %
b11101010101110100111111111111111111111 "
b11101010101110100111111111111111111111 0
b11000 .
1#
#1840000
0#
#1850000
b11001 .
b1110101010111010011111111111111111111 "
b1110101010111010011111111111111111111 0
b11001 %
1#
#1860000
0#
#1870000
b11010 %
b11101101010111010011111111111111111111 "
b11101101010111010011111111111111111111 0
b11010 .
1#
#1880000
0#
#1890000
b11011 .
b1110110101011101001111111111111111111 "
b1110110101011101001111111111111111111 0
b11011 %
1#
#1900000
0#
#1910000
b11100 %
b11101110101011101001111111111111111111 "
b11101110101011101001111111111111111111 0
b11100 .
1#
#1920000
0#
#1930000
b11101 .
b1110111010101110100111111111111111111 "
b1110111010101110100111111111111111111 0
b11101 %
1#
#1940000
0#
#1950000
b11110 %
b11101111010101110100111111111111111111 "
b11101111010101110100111111111111111111 0
b11110 .
1#
#1960000
0#
#1970000
b11111 .
b1110111101010111010011111111111111111 "
b1110111101010111010011111111111111111 0
b11111 %
1#
#1980000
0#
#1990000
b100000 %
b11101111101010111010011111111111111111 "
b11101111101010111010011111111111111111 0
b100000 .
1#
#2000000
0#
#2010000
b100001 .
b1110111110101011101001111111111111111 "
b1110111110101011101001111111111111111 0
b100001 %
1#
#2020000
0#
#2030000
b100010 %
b11101111110101011101001111111111111111 "
b11101111110101011101001111111111111111 0
b100010 .
1#
#2040000
0#
#2050000
b100011 .
b1110111111010101110100111111111111111 "
b1110111111010101110100111111111111111 0
b100011 %
1#
#2060000
0#
#2070000
b100100 %
b11101111111010101110100111111111111111 "
b11101111111010101110100111111111111111 0
b100100 .
1#
#2080000
0#
#2090000
b100101 .
b1110111111101010111010011111111111111 "
b1110111111101010111010011111111111111 0
b100101 %
1#
#2100000
0#
#2110000
b100110 %
b11101111111101010111010011111111111111 "
b11101111111101010111010011111111111111 0
b100110 .
1#
#2120000
0#
#2130000
b100111 .
b1110111111110101011101001111111111111 "
b1110111111110101011101001111111111111 0
b100111 %
1#
#2140000
0#
#2150000
b101000 %
b11101111111110101011101001111111111111 "
b11101111111110101011101001111111111111 0
b101000 .
1#
#2160000
0#
#2170000
b101001 .
b1110111111111010101110100111111111111 "
b1110111111111010101110100111111111111 0
b101001 %
1#
#2180000
0#
#2190000
b101010 %
b11101111111111010101110100111111111111 "
b11101111111111010101110100111111111111 0
b101010 .
1#
#2200000
0#
#2210000
b101011 .
b1110111111111101010111010011111111111 "
b1110111111111101010111010011111111111 0
b101011 %
1#
#2220000
0#
#2230000
b101100 %
b11101111111111101010111010011111111111 "
b11101111111111101010111010011111111111 0
b101100 .
1#
#2240000
0#
#2250000
b101101 .
b1110111111111110101011101001111111111 "
b1110111111111110101011101001111111111 0
b101101 %
1#
#2260000
0#
#2270000
b101110 %
b11101111111111110101011101001111111111 "
b11101111111111110101011101001111111111 0
b101110 .
1#
#2280000
0#
#2290000
b101111 .
b1110111111111111010101110100111111111 "
b1110111111111111010101110100111111111 0
b101111 %
1#
#2300000
0#
#2310000
b110000 %
b11101111111111111010101110100111111111 "
b11101111111111111010101110100111111111 0
b110000 .
1#
#2320000
0#
#2330000
b110001 .
b1110111111111111101010111010011111111 "
b1110111111111111101010111010011111111 0
b110001 %
1#
#2340000
0#
#2350000
b110010 %
b11101111111111111101010111010011111111 "
b11101111111111111101010111010011111111 0
b110010 .
1#
#2360000
0#
#2370000
b110011 .
b1110111111111111110101011101001111111 "
b1110111111111111110101011101001111111 0
b110011 %
1#
#2380000
0#
#2390000
b110100 %
b11101111111111111110101011101001111111 "
b11101111111111111110101011101001111111 0
b110100 .
1#
#2400000
0#
#2410000
b110101 .
b1110111111111111111010101110100111111 "
b1110111111111111111010101110100111111 0
b110101 %
1#
#2420000
0#
#2430000
b110110 %
b11101111111111111111010101110100111111 "
b11101111111111111111010101110100111111 0
b110110 .
1#
#2440000
0#
#2450000
b110111 .
b1110111111111111111101010111010011111 "
b1110111111111111111101010111010011111 0
b110111 %
1#
#2460000
0#
#2470000
b111000 %
b11101111111111111111101010111010011111 "
b11101111111111111111101010111010011111 0
b111000 .
1#
#2480000
0#
#2490000
b111001 .
b1110111111111111111110101011101001111 "
b1110111111111111111110101011101001111 0
b111001 %
1#
#2500000
0#
#2510000
b111010 %
b11101111111111111111110101011101001111 "
b11101111111111111111110101011101001111 0
b111010 .
1#
#2520000
0#
#2530000
b111011 .
b1110111111111111111111010101110100111 "
b1110111111111111111111010101110100111 0
b111011 %
1#
#2540000
0#
#2550000
b111100 %
b11101111111111111111111010101110100111 "
b11101111111111111111111010101110100111 0
b111100 .
1#
#2560000
0#
#2570000
b111101 .
b1110111111111111111111101010111010011 "
b1110111111111111111111101010111010011 0
b111101 %
1#
#2580000
0#
#2590000
b111110 %
b11101111111111111111111101010111010011 "
b11101111111111111111111101010111010011 0
b111110 .
1#
#2600000
0#
#2610000
b111111 .
b1110111111111111111111110101011101001 "
b1110111111111111111111110101011101001 0
b111111 %
1#
#2620000
0#
#2630000
b0 %
b11101111111111111111111110101011101001 "
b11101111111111111111111110101011101001 0
b1000000 .
1#
#2640000
0#
#2650000
b1000001 .
b1110111111111111111111111010101110100 "
b1110111111111111111111111010101110100 0
1!
b1 %
1#
#2660000
0#
#2670000
1&
b10 %
0!
b1000010 .
1#
#2680000
0#
#2690000
b0 .
b0 /
b0 "
b0 0
0&
b0 $
b1011010 (
b1011010 -
b11111111111111111111111111100010 '
b11111111111111111111111111100010 ,
b0 %
1#
b1011010 +
b1111111111111111111111111111111111111111111111111111111111100010 *
1)
#2700000
0#
#2710000
b1 %
b11111111111111111111111111111111111111111111111111111010101110100 $
b1011010 "
b1011010 0
b11111111111111111111111111100010 /
b1 .
1#
0)
#2720000
0#
#2730000
b10 .
b10 %
1#
#2740000
0#
#2750000
b11 %
b101101 "
b101101 0
b11 .
1#
#2760000
0#
#2770000
b100 .
b1111111111111111111111111110001000000000000000000000000000101101 "
b1111111111111111111111111110001000000000000000000000000000101101 0
b100 %
1#
#2780000
0#
#2790000
b101 %
b111111111111111111111111111000100000000000000000000000000010110 "
b111111111111111111111111111000100000000000000000000000000010110 0
b101 .
1#
#2800000
0#
#2810000
b110 .
b110 %
1#
#2820000
0#
#2830000
b111 %
b11111111111111111111111111100010000000000000000000000000001011 "
b11111111111111111111111111100010000000000000000000000000001011 0
b111 .
1#
#2840000
0#
#2850000
b1000 .
b11111111111111111111111101101010000000000000000000000000001011 "
b11111111111111111111111101101010000000000000000000000000001011 0
b1000 %
1#
#2860000
0#
#2870000
b1001 %
b1111111111111111111111110110101000000000000000000000000000101 "
b1111111111111111111111110110101000000000000000000000000000101 0
b1001 .
1#
#2880000
0#
#2890000
b1010 .
b1111111111111111111111100111101000000000000000000000000000101 "
b1111111111111111111111100111101000000000000000000000000000101 0
b1010 %
1#
#2900000
0#
#2910000
b1011 %
b111111111111111111111110011110100000000000000000000000000010 "
b111111111111111111111110011110100000000000000000000000000010 0
b1011 .
1#
#2920000
0#
#2930000
b1100 .
b1100 %
1#
#2940000
0#
#2950000
b1101 %
b11111111111111111111111001111010000000000000000000000000001 "
b11111111111111111111111001111010000000000000000000000000001 0
b1101 .
1#
#2960000
0#
#2970000
b1110 .
b11111111111111111111101010111010000000000000000000000000001 "
b11111111111111111111101010111010000000000000000000000000001 0
b1110 %
1#
#2980000
0#
#2990000
b1111 %
b1111111111111111111110101011101000000000000000000000000000 "
b1111111111111111111110101011101000000000000000000000000000 0
b1111 .
1#
#3000000
0#
#3010000
b10000 .
b10000 %
1#
#3020000
0#
#3030000
b10001 %
b111111111111111111111010101110100000000000000000000000000 "
b111111111111111111111010101110100000000000000000000000000 0
b10001 .
1#
#3040000
0#
#3050000
b10010 .
b10010 %
1#
#3060000
0#
#3070000
b10011 %
b11111111111111111111101010111010000000000000000000000000 "
b11111111111111111111101010111010000000000000000000000000 0
b10011 .
1#
#3080000
0#
#3090000
b10100 .
b10100 %
1#
#3100000
0#
#3110000
b10101 %
b1111111111111111111110101011101000000000000000000000000 "
b1111111111111111111110101011101000000000000000000000000 0
b10101 .
1#
#3120000
0#
#3130000
b10110 .
b10110 %
1#
#3140000
0#
#3150000
b10111 %
b111111111111111111111010101110100000000000000000000000 "
b111111111111111111111010101110100000000000000000000000 0
b10111 .
1#
#3160000
0#
#3170000
b11000 .
b11000 %
1#
#3180000
0#
#3190000
b11001 %
b11111111111111111111101010111010000000000000000000000 "
b11111111111111111111101010111010000000000000000000000 0
b11001 .
1#
#3200000
0#
#3210000
b11010 .
b11010 %
1#
#3220000
0#
#3230000
b11011 %
b1111111111111111111110101011101000000000000000000000 "
b1111111111111111111110101011101000000000000000000000 0
b11011 .
1#
#3240000
0#
#3250000
b11100 .
b11100 %
1#
#3260000
0#
#3270000
b11101 %
b111111111111111111111010101110100000000000000000000 "
b111111111111111111111010101110100000000000000000000 0
b11101 .
1#
#3280000
0#
#3290000
b11110 .
b11110 %
1#
#3300000
0#
#3310000
b11111 %
b11111111111111111111101010111010000000000000000000 "
b11111111111111111111101010111010000000000000000000 0
b11111 .
1#
#3320000
0#
#3330000
b100000 .
b100000 %
1#
#3340000
0#
#3350000
b100001 %
b1111111111111111111110101011101000000000000000000 "
b1111111111111111111110101011101000000000000000000 0
b100001 .
1#
#3360000
0#
#3370000
b100010 .
b100010 %
1#
#3380000
0#
#3390000
b100011 %
b111111111111111111111010101110100000000000000000 "
b111111111111111111111010101110100000000000000000 0
b100011 .
1#
#3400000
0#
#3410000
b100100 .
b100100 %
1#
#3420000
0#
#3430000
b100101 %
b11111111111111111111101010111010000000000000000 "
b11111111111111111111101010111010000000000000000 0
b100101 .
1#
#3440000
0#
#3450000
b100110 .
b100110 %
1#
#3460000
0#
#3470000
b100111 %
b1111111111111111111110101011101000000000000000 "
b1111111111111111111110101011101000000000000000 0
b100111 .
1#
#3480000
0#
#3490000
b101000 .
b101000 %
1#
#3500000
0#
#3510000
b101001 %
b111111111111111111111010101110100000000000000 "
b111111111111111111111010101110100000000000000 0
b101001 .
1#
#3520000
0#
#3530000
b101010 .
b101010 %
1#
#3540000
0#
#3550000
b101011 %
b11111111111111111111101010111010000000000000 "
b11111111111111111111101010111010000000000000 0
b101011 .
1#
#3560000
0#
#3570000
b101100 .
b101100 %
1#
#3580000
0#
#3590000
b101101 %
b1111111111111111111110101011101000000000000 "
b1111111111111111111110101011101000000000000 0
b101101 .
1#
#3600000
0#
#3610000
b101110 .
b101110 %
1#
#3620000
0#
#3630000
b101111 %
b111111111111111111111010101110100000000000 "
b111111111111111111111010101110100000000000 0
b101111 .
1#
#3640000
0#
#3650000
b110000 .
b110000 %
1#
#3660000
0#
#3670000
b110001 %
b11111111111111111111101010111010000000000 "
b11111111111111111111101010111010000000000 0
b110001 .
1#
#3680000
0#
#3690000
b110010 .
b110010 %
1#
#3700000
0#
#3710000
b110011 %
b1111111111111111111110101011101000000000 "
b1111111111111111111110101011101000000000 0
b110011 .
1#
#3720000
0#
#3730000
b110100 .
b110100 %
1#
#3740000
0#
#3750000
b110101 %
b111111111111111111111010101110100000000 "
b111111111111111111111010101110100000000 0
b110101 .
1#
#3760000
0#
#3770000
b110110 .
b110110 %
1#
#3780000
0#
#3790000
b110111 %
b11111111111111111111101010111010000000 "
b11111111111111111111101010111010000000 0
b110111 .
1#
#3800000
0#
#3810000
b111000 .
b111000 %
1#
#3820000
0#
#3830000
b111001 %
b1111111111111111111110101011101000000 "
b1111111111111111111110101011101000000 0
b111001 .
1#
#3840000
0#
#3850000
b111010 .
b111010 %
1#
#3860000
0#
#3870000
b111011 %
b111111111111111111111010101110100000 "
b111111111111111111111010101110100000 0
b111011 .
1#
#3880000
0#
#3890000
b111100 .
b111100 %
1#
#3900000
0#
#3910000
b111101 %
b11111111111111111111101010111010000 "
b11111111111111111111101010111010000 0
b111101 .
1#
#3920000
0#
#3930000
b111110 .
b111110 %
1#
#3940000
0#
#3950000
b111111 %
b1111111111111111111110101011101000 "
b1111111111111111111110101011101000 0
b111111 .
1#
#3960000
0#
#3970000
b1000000 .
b0 %
1#
#3980000
0#
#3990000
b1 %
1!
b111111111111111111111010101110100 "
b111111111111111111111010101110100 0
b1000001 .
1#
#4000000
0#
#4010000
b1000010 .
0!
1&
b10 %
1#
#4020000
0#
#4030000
0&
b0 $
b11111111111111111111111110100110 (
b11111111111111111111111110100110 -
b0 %
b0 /
b0 "
b0 0
b0 .
1#
b1111111111111111111111111111111111111111111111111111111110100110 +
1)
#4040000
0#
#4050000
b1 .
b11111111111111111111111110100110 "
b11111111111111111111111110100110 0
b11111111111111111111111111100010 /
b1 %
b101010001100 $
1#
0)
#4060000
0#
#4070000
b10 %
b10 .
1#
#4080000
0#
#4090000
b11 .
b1111111111111111111111111010011 "
b1111111111111111111111111010011 0
b11 %
1#
#4100000
0#
#4110000
b100 %
b1111111111111111111111111110001001111111111111111111111111010011 "
b1111111111111111111111111110001001111111111111111111111111010011 0
b100 .
1#
#4120000
0#
#4130000
b101 .
b111111111111111111111111111000100111111111111111111111111101001 "
b111111111111111111111111111000100111111111111111111111111101001 0
b101 %
1#
#4140000
0#
#4150000
b110 %
b111111111111111111111111101001100111111111111111111111111101001 "
b111111111111111111111111101001100111111111111111111111111101001 0
b110 .
1#
#4160000
0#
#4170000
b111 .
b11111111111111111111111110100110011111111111111111111111110100 "
b11111111111111111111111110100110011111111111111111111111110100 0
b111 %
1#
#4180000
0#
#4190000
b1000 %
b1000 .
1#
#4200000
0#
#4210000
b1001 .
b1111111111111111111111111010011001111111111111111111111111010 "
b1111111111111111111111111010011001111111111111111111111111010 0
b1001 %
1#
#4220000
0#
#4230000
b1010 %
b1010 .
1#
#4240000
0#
#4250000
b1011 .
b111111111111111111111111101001100111111111111111111111111101 "
b111111111111111111111111101001100111111111111111111111111101 0
b1011 %
1#
#4260000
0#
#4270000
b1100 %
b111111111111111111111101110001100111111111111111111111111101 "
b111111111111111111111101110001100111111111111111111111111101 0
b1100 .
1#
#4280000
0#
#4290000
b1101 .
b11111111111111111111110111000110011111111111111111111111110 "
b11111111111111111111110111000110011111111111111111111111110 0
b1101 %
1#
#4300000
0#
#4310000
b1110 %
b1110 .
1#
#4320000
0#
#4330000
b1111 .
b1111111111111111111111011100011001111111111111111111111111 "
b1111111111111111111111011100011001111111111111111111111111 0
b1111 %
1#
#4340000
0#
#4350000
b10000 %
b1111111111111111111101100100011001111111111111111111111111 "
b1111111111111111111101100100011001111111111111111111111111 0
b10000 .
1#
#4360000
0#
#4370000
b10001 .
b111111111111111111110110010001100111111111111111111111111 "
b111111111111111111110110010001100111111111111111111111111 0
b10001 %
1#
#4380000
0#
#4390000
b10010 %
b111111111111111111100111010001100111111111111111111111111 "
b111111111111111111100111010001100111111111111111111111111 0
b10010 .
1#
#4400000
0#
#4410000
b10011 .
b11111111111111111110011101000110011111111111111111111111 "
b11111111111111111110011101000110011111111111111111111111 0
b10011 %
1#
#4420000
0#
#4430000
b10100 %
b11111111111111111100100101000110011111111111111111111111 "
b11111111111111111100100101000110011111111111111111111111 0
b10100 .
1#
#4440000
0#
#4450000
b10101 .
b1111111111111111110010010100011001111111111111111111111 "
b1111111111111111110010010100011001111111111111111111111 0
b10101 %
1#
#4460000
0#
#4470000
b10110 %
b1111111111111111100011010100011001111111111111111111111 "
b1111111111111111100011010100011001111111111111111111111 0
b10110 .
1#
#4480000
0#
#4490000
b10111 .
b111111111111111110001101010001100111111111111111111111 "
b111111111111111110001101010001100111111111111111111111 0
b10111 %
1#
#4500000
0#
#4510000
b11000 %
b111111111111111100010101010001100111111111111111111111 "
b111111111111111100010101010001100111111111111111111111 0
b11000 .
1#
#4520000
0#
#4530000
b11001 .
b11111111111111110001010101000110011111111111111111111 "
b11111111111111110001010101000110011111111111111111111 0
b11001 %
1#
#4540000
0#
#4550000
b11010 %
b11111111111111100010010101000110011111111111111111111 "
b11111111111111100010010101000110011111111111111111111 0
b11010 .
1#
#4560000
0#
#4570000
b11011 .
b1111111111111110001001010100011001111111111111111111 "
b1111111111111110001001010100011001111111111111111111 0
b11011 %
1#
#4580000
0#
#4590000
b11100 %
b1111111111111100010001010100011001111111111111111111 "
b1111111111111100010001010100011001111111111111111111 0
b11100 .
1#
#4600000
0#
#4610000
b11101 .
b111111111111110001000101010001100111111111111111111 "
b111111111111110001000101010001100111111111111111111 0
b11101 %
1#
#4620000
0#
#4630000
b11110 %
b111111111111100010000101010001100111111111111111111 "
b111111111111100010000101010001100111111111111111111 0
b11110 .
1#
#4640000
0#
#4650000
b11111 .
b11111111111110001000010101000110011111111111111111 "
b11111111111110001000010101000110011111111111111111 0
b11111 %
1#
#4660000
0#
#4670000
b100000 %
b11111111111100010000010101000110011111111111111111 "
b11111111111100010000010101000110011111111111111111 0
b100000 .
1#
#4680000
0#
#4690000
b100001 .
b1111111111110001000001010100011001111111111111111 "
b1111111111110001000001010100011001111111111111111 0
b100001 %
1#
#4700000
0#
