lab10_16bit_ieeeFPMultiplier/FPMultiplier16bit/fp_norm.v
`timescale 1ns / 1ps

module fadd_norm (rm,is_nan,is_inf,inf_nan_frac,sign,temp_exp,cf,s);
	//1 5 10
	//1 8 23
	input [26:0] cf;
	input [9:0] inf_nan_frac;
	input [4:0] temp_exp;
	input [1:0] rm;
	input is_nan,is_inf;
	input sign;
	output [15:0] s;
	wire [13:0] f3,f2,f1,f0;
	wire [14:0] cal_frac= cf[21:7];
	
	//從左邊找到第一個1
	wire [3:0] zeros;
	assign zeros[3] = ~|cal_frac[13:6]; // 8-bit 0
	assign f3 = zeros[3]? {cal_frac[5:0],8'b0} : cal_frac[13:0];
	assign zeros[2] = ~|f3[13:10]; // 4-bit 0
	assign f2 = zeros[2]? {f3[9:0], 4'b0} : f3;
	assign zeros[1] = ~|f2[13:12]; // 2-bit 0
	assign f1 = zeros[1]? {f2[11:0], 2'b0} : f2;
	assign zeros[0] = ~f1[13]; // 1-bit 0
	assign f0 = zeros[0]? {f1[12:0], 1'b0} : f1;
	
	//位移以及修改exponent
	reg [13:0] frac0;
	reg [4:0] exp0;
	always @ * begin
		if (cal_frac[14]) begin
			frac0 = cal_frac[14:1]; // 1x.xxxxxxxxxxxxxxxxxxxxxxx xxx
			exp0 = temp_exp + 5'h1; // 1.xxxxxxxxxxxxxxxxxxxxxxx xxx
		end 
		else begin
			if ((temp_exp > zeros) && (f0[13])) begin // a normalized number
				exp0 = temp_exp - zeros;
				frac0 = f0; // 01.xxxxxxxxxxxxxxxxxxxxxxx xxx
			end
			else begin // is a denormalized number or 0
				exp0 = 0;
				if (temp_exp != 0) // (e - 127) = ((e - 1) - 126)
					frac0 = cal_frac[13:0] << (temp_exp - 5'h1);
				else frac0 = cal_frac[13:0];
			end
		end
	end

	//依照選取的模式執行round
	wire frac_plus_1 = // for rounding
	~rm[1] & ~rm[0] & frac0[2] & (frac0[1] | frac0[0]) |
	~rm[1] & ~rm[0] & frac0[2] & ~frac0[1] & ~frac0[0] & frac0[3] |
	~rm[1] & rm[0] & (frac0[2] | frac0[1] | frac0[0]) & sign |
	rm[1] & ~rm[0] & (frac0[2] | frac0[1] | frac0[0]) & ~sign;
	wire [11:0] frac_round = {1'b0,frac0[13:3]} + frac_plus_1;
	wire [4:0] exponent = frac_round[11]? exp0 + 5'h1  : exp0 ;
	wire overflow = &exp0 | &exponent;
	assign s = final_result(overflow, rm, sign, is_nan, is_inf, exponent, frac_round[9:0], inf_nan_frac);
	//處理例外狀況
	function [15:0] final_result;
		input overflow;
		input [1:0] rm;
		input sign, is_nan, is_inf;
		input [4:0] exponent;
		input [9:0] fraction, inf_nan_frac;
		casex ({overflow, rm, sign, is_nan, is_inf})
			6'b1_00_x_0_x : final_result = {sign,5'h1f,10'h0}; // inf
			6'b1_01_0_0_x : final_result = {sign,5'h1e,10'h3ff}; // max
			6'b1_01_1_0_x : final_result = {sign,5'h1f,10'h0}; // inf
			6'b1_10_0_0_x : final_result = {sign,5'h1f,10'h0}; // inf
			6'b1_10_1_0_x : final_result = {sign,5'h1e,10'h3ff}; // max
			6'b1_11_x_0_x : final_result = {sign,5'h1e,10'h3ff}; // max
			6'b0_xx_x_0_0 : final_result = {sign,exponent,fraction}; // nor
			6'bx_xx_x_1_x : final_result = {1'b1,5'h1f,inf_nan_frac}; // nan
			6'bx_xx_x_0_1 : final_result = {sign,5'h1f,inf_nan_frac}; // inf
			default : final_result = {sign,5'h0,10'h0}; // 0
		endcase
	endfunction
endmodule

lab10_16bit_ieeeFPMultiplier/FPMultiplier16bit/fp_reg_cal_norm.v
`timescale 1ns / 1ps
//////////////////////////////////////////////////////////////////////////////////
// Company: 
// Engineer: 
// 
// Create Date:    11:26:12 03/24/2017 
// Design Name: 
// Module Name:    float_adder 
// Project Name: 
// Target Devices: 
// Tool versions: 
// Description: 
//
// Dependencies: 
//
// Revision: 
// Revision 0.01 - File Created
// Additional Comments: 
//
//////////////////////////////////////////////////////////////////////////////////
module reg_cal_norm (c_rm,c_is_nan,c_is_inf,c_inf_nan_frac,c_sign,c_exp,
c_frac,clk,clrn,e,n_rm,n_is_nan,n_is_inf,
n_inf_nan_frac,n_sign,n_exp,n_frac); // pipeline regs
	input [26:0] c_frac;
	input [9:0] c_inf_nan_frac;
	input [4:0] c_exp;
	input [1:0] c_rm;
	input c_is_nan, c_is_inf, c_sign;
	input e; // e: enable
	input clk, clrn; // clock and reset
	output reg [26:0] n_frac;
	output reg [9:0] n_inf_nan_frac;
	output reg [4:0] n_exp;
	output reg [1:0] n_rm;
	output reg n_is_nan,n_is_inf,n_sign;
	always @ (posedge clk or negedge clrn) begin
		if (!clrn) begin
			n_rm <= 0;
			n_is_nan <= 0;
			n_is_inf <= 0;
			n_inf_nan_frac <= 0;
			n_sign <= 0;
			n_exp <= 0;
			n_frac <= 0;
		end else if (e) begin
			n_rm <= c_rm;
			n_is_nan <= c_is_nan;
			n_is_inf <= c_is_inf;
			n_inf_nan_frac <= c_inf_nan_frac;
			n_sign <= c_sign;
			n_exp <= c_exp;
			n_frac <= c_frac;
		end
	end
endmodule

lab10_16bit_ieeeFPMultiplier/FPMultiplier16bit/fp_cal.v
`timescale 1ns / 1ps

module fadd_cal (op_sub,large_frac24,small_frac27, cal_frac); // calculation
	//1 5 10
	input [10:0] large_frac24;
	input op_sub;
	input [10:0] small_frac27;
	output [26:0] cal_frac;
	//補上grs,以及避免溢位狀況,共28bit
	/*//23+3+1
	wire [14:0] aligned_large_frac = {1'b0,large_frac24,3'b000};
	wire [14:0] aligned_small_frac = {1'b0,small_frac27};
	//相減或相加
	assign cal_frac = op_sub?
	aligned_large_frac - aligned_small_frac :
	aligned_large_frac + aligned_small_frac;*/

	assign cal_frac=small_frac27*large_frac24;


endmodule

lab10_16bit_ieeeFPMultiplier/FPMultiplier16bit/fp_reg_align_cal.v
`timescale 1ns / 1ps
//////////////////////////////////////////////////////////////////////////////////
// Company: 
// Engineer: 
// 
// Create Date:    12:16:19 04/07/2017 
// Design Name: 
// Module Name:    float_control_2 
// Project Name: 
// Target Devices: 
// Tool versions: 
// Description: 
//
// Dependencies: 
//
// Revision: 
// Revision 0.01 - File Created
// Additional Comments: 
//
//////////////////////////////////////////////////////////////////////////////////
module reg_align_cal (a_rm,a_is_nan,a_is_inf,a_inf_nan_frac,a_sign,a_exp,
a_op_sub,a_large_frac,a_small_frac,clk,clrn,e,c_rm,
c_is_nan,c_is_inf,c_inf_nan_frac,c_sign,c_exp,
c_op_sub,c_large_frac,c_small_frac); // pipeline regs
	input [10:0] a_small_frac;
	input [10:0] a_large_frac;
	input [9:0] a_inf_nan_frac;
	input [4:0] a_exp;
	input [1:0] a_rm;
	input a_is_nan, a_is_inf, a_sign, a_op_sub;
	input e; // e: enable
	input clk, clrn; // clock and reset
	output reg [10:0] c_small_frac;
	output reg [10:0] c_large_frac;
	output reg [9:0] c_inf_nan_frac;
	output reg [4:0] c_exp;
	output reg [1:0] c_rm;
	output reg c_is_nan,c_is_inf,c_sign,c_op_sub;
	always @ (posedge clk or negedge clrn) begin
		if (!clrn) begin
			c_rm <= 0;
			c_is_nan <= 0;
			c_is_inf <= 0;
			c_inf_nan_frac <= 0;
			c_sign <= 0;
			c_exp <= 0;
			c_op_sub <= 0;
			c_large_frac <= 0;
			c_small_frac <= 0;
		end else if (e) begin
			c_rm <= a_rm;
			c_is_nan <= a_is_nan;
			c_is_inf <= a_is_inf;
			c_inf_nan_frac <= a_inf_nan_frac;
			c_sign <= a_sign;
			c_exp <= a_exp;
			c_op_sub <= a_op_sub;
			c_large_frac <= a_large_frac;
			c_small_frac <= a_small_frac;
		end
	end
endmodule

lab10_16bit_ieeeFPMultiplier/FPMultiplier16bit/fp_align.v
`timescale 1ns / 1ps

module fadd_align (a,b,sub,s_is_nan,s_is_inf,inf_nan_frac,sign,temp_exp,
op_sub,large_frac24,small_frac24); //alignment stage
	input [15:0] a,b;
	input sub;
	//1 8 23 
	//1 5 10 
	output [10:0] small_frac24;
	output [10:0] large_frac24;
	output [9:0] inf_nan_frac;
	output [4:0] temp_exp;
	output s_is_nan;
	output s_is_inf;
	output sign;
	output op_sub;
	
	wire [15:0] fp_large =  a;
	wire [15:0] fp_small =  b;

	//轉成1.f格式
	wire fp_large_hidden_bit = |fp_large[14:10];
	wire fp_small_hidden_bit = |fp_small[14:10];
	wire [10:0] large_frac24 = {fp_large_hidden_bit,fp_large[9:0]};
	wire [10:0] small_frac24 = {fp_small_hidden_bit,fp_small[9:0]};

	//儲存較大數的exponent
	assign temp_exp = fp_large[14:10]+fp_small[14:10]-15;

	//判斷正負
	assign sign =b[15] ^ a[15];

	//例外狀況
	wire fp_large_expo_is_ff = &fp_large[14:10]; // exp == 0xff
	wire fp_small_expo_is_ff = &fp_small[14:10];
	wire fp_large_frac_is_00 = ~|fp_large[9:0]; // frac == 0x0
	wire fp_small_frac_is_00 = ~|fp_small[9:0];
	wire fp_large_is_inf=fp_large_expo_is_ff & fp_large_frac_is_00;
	wire fp_small_is_inf=fp_small_expo_is_ff & fp_small_frac_is_00;
	wire fp_large_is_nan=fp_large_expo_is_ff & ~fp_large_frac_is_00;
	wire fp_small_is_nan=fp_small_expo_is_ff & ~fp_small_frac_is_00;
	assign s_is_inf = fp_large_is_inf | fp_small_is_inf;
	wire s_is_nan = fp_large_is_nan | fp_small_is_nan | ((sub ^ fp_small[15] ^ fp_large[15]) & fp_large_is_inf & fp_small_is_inf);
	wire [9:0] nan_frac = (a[8:0] > b[8:0])?	{1'b1,a[8:0]} : {1'b1,b[8:0]};
	assign inf_nan_frac = s_is_nan? nan_frac : 10'h0;


	/*//ea-eb
	wire [4:0] exp_diff = fp_large[14:10] - fp_small[14:10];
	wire small_den_only = (fp_large[14:10] != 0) & (fp_small[14:10] == 0);
	
	//計算需要位移幾位,並且位移
	wire [4:0] shift_amount = small_den_only? exp_diff - 5'h1 : exp_diff;
	wire [23:0] small_frac50 = (shift_amount >= 13)? {13'h0,small_frac24} : {small_frac24,13'h0} >> shift_amount;

	//留下11bit以及保護.循環位,計算多出來的位數,使用reduction OR簡化成1bit
	assign small_frac27 = {small_frac50[23:11],|small_frac50[10:0]};*/
endmodule

lab10_16bit_ieeeFPMultiplier/FPMultiplier16bit/fp_adder.v
`include "fp_align.v"
`include "fp_reg_align_cal.v"
`include "fp_cal.v"
`include "fp_norm.v"
`include "fp_reg_cal_norm.v"
`timescale 1ns / 1ps

module pipelined_fpadder (a,b,sub,rm,s,clk,clrn,e); // pipelined fp adder
	input clk, clrn; // clock and reset
	input [15:0] a, b; // fp a and b
	input [1:0] rm; // round mode
	input sub; // 1: sub; 0: add
	input e; // enable
	output [15:0] s; // fp output
	//1 5 10

	// exe1: alignment stage
	wire [10:0] a_small_frac;
	wire [10:0] a_large_frac;
	wire [9:0] a_inf_nan_frac;
	wire [4:0] a_exp;
	wire a_is_nan,a_is_inf;
	wire a_sign;
	wire a_op_sub;
	fadd_align alignment (a,b,sub,a_is_nan,a_is_inf,a_inf_nan_frac,a_sign,
	a_exp,a_op_sub,a_large_frac,a_small_frac);
	
	// pipelined registers
	wire [10:0] c_small_frac;
	wire [10:0] c_large_frac;
	wire [9:0] c_inf_nan_frac;
	wire [4:0] c_exp;
	wire [1:0] c_rm;
	wire c_is_nan,c_is_inf;
	wire c_sign;
	wire c_op_sub;
	reg_align_cal reg_ac (rm,a_is_nan,a_is_inf,a_inf_nan_frac,a_sign,a_exp,
	a_op_sub,a_large_frac,a_small_frac,clk,clrn,e,
	c_rm,c_is_nan,c_is_inf,c_inf_nan_frac,c_sign,
	c_exp,c_op_sub,c_large_frac,c_small_frac);
	
	// exe2: calculation stage
	wire [26:0] c_frac;
	fadd_cal calculation (c_op_sub,c_large_frac,c_small_frac,c_frac);
	
	// pipelined registers
	wire [26:0] n_frac;
	wire [9:0] n_inf_nan_frac;
	wire [4:0] n_exp;
	wire [1:0] n_rm;
	wire n_is_nan,n_is_inf;
	wire n_sign;
	reg_cal_norm reg_cn (c_rm,c_is_nan,c_is_inf,c_inf_nan_frac,c_sign,c_exp,
	c_frac,clk,clrn,e,n_rm,n_is_nan,n_is_inf,
	n_inf_nan_frac,n_sign,n_exp,n_frac);


	// exe3: normalization stage
	fadd_norm normalization (n_rm,n_is_nan,n_is_inf,n_inf_nan_frac,n_sign,
	n_exp,n_frac,s);


endmodule

lab10_16bit_ieeeFPMultiplier/FPMultiplier16bit/testbench.v
`include "fp_adder.v"//
`timescale 1ns / 1ps

module test_bench;
reg clk; //clock
reg clrn; //負緣時清空
reg[15:0] a;
reg[15:0] b;
reg en;
wire [15:0] result;
pipelined_fpadder test(a,b,1'b0,2'd0,result,clk,clrn,en);


initial #0 clk = 1'b1;
always #10 clk = ~clk;
  
initial begin
	a = 16'h4500;
	b = 16'h4700;
	en = 0;
	#0 clrn = 1'b0;
	#5 clrn = 1'b0;
	#10 clrn = 1'b1;
	en = 1'b1;
	#50
	if(result==16'h5060)
		$display("----------Correct!----------");
	else
		$display("----------Wrong!----------");
	$display("Ans:%x, yours:%x\n",16'h5060,result);
	a = 16'h4300;
	b = 16'hC500;
	en = 0;
	#0 clrn = 1'b0;
	#5 clrn = 1'b0;
	#10 clrn = 1'b1;
	en = 1'b1;
	#50
	if(result==16'hCC60)
		$display("----------Correct!----------");
	else
		$display("----------Wrong!----------");
	$display("Ans:%x, yours:%x\n",16'hCC60,result);
	a = 16'h7BFF;
	b = 16'h7BFF;
	en = 0;
	#0 clrn = 1'b0;
	#5 clrn = 1'b0;
	#10 clrn = 1'b1;
	en = 1'b1;
	#50
	$display("----------Exp!----------");
	$display("Ans:x, yours:%x\n",result);
	#500 $finish;
end

initial begin
	$dumpfile("fpadder.vcd");
	$dumpvars;
end

endmodule

lab10_16bit_ieeeFPMultiplier/FPMultiplier16bit/fpadder.vcd
$date
	Mon May 21 19:03:18 2018
$end
$version
	Icarus Verilog
$end
$timescale
	1ps
$end
$scope module test_bench $end
$var wire 16 ! result [15:0] $end
$var reg 16 " a [15:0] $end
$var reg 16 # b [15:0] $end
$var reg 1 $ clk $end
$var reg 1 % clrn $end
$var reg 1 & en $end
$scope module test $end
$var wire 16 ' a [15:0] $end
$var wire 1 ( a_op_sub $end
$var wire 16 ) b [15:0] $end
$var wire 1 $ clk $end
$var wire 1 % clrn $end
$var wire 1 & e $end
$var wire 2 * rm [1:0] $end
$var wire 1 + sub $end
$var wire 16 , s [15:0] $end
$var wire 1 - n_sign $end
$var wire 2 . n_rm [1:0] $end
$var wire 1 / n_is_nan $end
$var wire 1 0 n_is_inf $end
$var wire 10 1 n_inf_nan_frac [9:0] $end
$var wire 27 2 n_frac [26:0] $end
$var wire 5 3 n_exp [4:0] $end
$var wire 11 4 c_small_frac [10:0] $end
$var wire 1 5 c_sign $end
$var wire 2 6 c_rm [1:0] $end
$var wire 1 7 c_op_sub $end
$var wire 11 8 c_large_frac [10:0] $end
$var wire 1 9 c_is_nan $end
$var wire 1 : c_is_inf $end
$var wire 10 ; c_inf_nan_frac [9:0] $end
$var wire 27 < c_frac [26:0] $end
$var wire 5 = c_exp [4:0] $end
$var wire 11 > a_small_frac [10:0] $end
$var wire 1 ? a_sign $end
$var wire 11 @ a_large_frac [10:0] $end
$var wire 1 A a_is_nan $end
$var wire 1 B a_is_inf $end
$var wire 10 C a_inf_nan_frac [9:0] $end
$var wire 5 D a_exp [4:0] $end
$scope module alignment $end
$var wire 16 E a [15:0] $end
$var wire 16 F b [15:0] $end
$var wire 16 G fp_large [15:0] $end
$var wire 1 H fp_large_is_inf $end
$var wire 1 I fp_large_is_nan $end
$var wire 16 J fp_small [15:0] $end
$var wire 1 K fp_small_is_inf $end
$var wire 1 L fp_small_is_nan $end
$var wire 1 ( op_sub $end
$var wire 1 B s_is_inf $end
$var wire 1 A s_is_nan $end
$var wire 1 ? sign $end
$var wire 1 + sub $end
$var wire 5 M temp_exp [4:0] $end
$var wire 11 N small_frac24 [10:0] $end
$var wire 10 O nan_frac [9:0] $end
$var wire 11 P large_frac24 [10:0] $end
$var wire 10 Q inf_nan_frac [9:0] $end
$var wire 1 R fp_small_hidden_bit $end
$var wire 1 S fp_small_frac_is_00 $end
$var wire 1 T fp_small_expo_is_ff $end
$var wire 1 U fp_large_hidden_bit $end
$var wire 1 V fp_large_frac_is_00 $end
$var wire 1 W fp_large_expo_is_ff $end
$upscope $end
$scope module calculation $end
$var wire 11 X small_frac27 [10:0] $end
$var wire 1 7 op_sub $end
$var wire 11 Y large_frac24 [10:0] $end
$var wire 27 Z cal_frac [26:0] $end
$upscope $end
$scope module normalization $end
$var wire 1 [ frac_plus_1 $end
$var wire 1 \ overflow $end
$var wire 4 ] zeros [3:0] $end
$var wire 5 ^ temp_exp [4:0] $end
$var wire 1 - sign $end
$var wire 16 _ s [15:0] $end
$var wire 2 ` rm [1:0] $end
$var wire 1 / is_nan $end
$var wire 1 0 is_inf $end
$var wire 10 a inf_nan_frac [9:0] $end
$var wire 12 b frac_round [11:0] $end
$var wire 14 c f3 [13:0] $end
$var wire 14 d f2 [13:0] $end
$var wire 14 e f1 [13:0] $end
$var wire 14 f f0 [13:0] $end
$var wire 5 g exponent [4:0] $end
$var wire 27 h cf [26:0] $end
$var wire 15 i cal_frac [14:0] $end
$var reg 5 j exp0 [4:0] $end
$var reg 14 k frac0 [13:0] $end
$scope function final_result $end
$var reg 5 l exponent [4:0] $end
$var reg 16 m final_result [15:0] $end
$var reg 10 n fraction [9:0] $end
$var reg 10 o inf_nan_frac [9:0] $end
$var reg 1 p is_inf $end
$var reg 1 q is_nan $end
$var reg 1 r overflow $end
$var reg 2 s rm [1:0] $end
$var reg 1 t sign $end
$upscope $end
$upscope $end
$scope module reg_ac $end
$var wire 5 u a_exp [4:0] $end
$var wire 10 v a_inf_nan_frac [9:0] $end
$var wire 1 B a_is_inf $end
$var wire 1 A a_is_nan $end
$var wire 11 w a_large_frac [10:0] $end
$var wire 1 ( a_op_sub $end
$var wire 2 x a_rm [1:0] $end
$var wire 1 ? a_sign $end
$var wire 11 y a_small_frac [10:0] $end
$var wire 1 $ clk $end
$var wire 1 % clrn $end
$var wire 1 & e $end
$var reg 5 z c_exp [4:0] $end
$var reg 10 { c_inf_nan_frac [9:0] $end
$var reg 1 : c_is_inf $end
$var reg 1 9 c_is_nan $end
$var reg 11 | c_large_frac [10:0] $end
$var reg 1 7 c_op_sub $end
$var reg 2 } c_rm [1:0] $end
$var reg 1 5 c_sign $end
$var reg 11 ~ c_small_frac [10:0] $end
$upscope $end
$scope module reg_cn $end
$var wire 5 !" c_exp [4:0] $end
$var wire 27 "" c_frac [26:0] $end
$var wire 10 #" c_inf_nan_frac [9:0] $end
$var wire 1 : c_is_inf $end
$var wire 1 9 c_is_nan $end
$var wire 2 $" c_rm [1:0] $end
$var wire 1 5 c_sign $end
$var wire 1 $ clk $end
$var wire 1 % clrn $end
$var wire 1 & e $end
$var reg 5 %" n_exp [4:0] $end
$var reg 27 &" n_frac [26:0] $end
$var reg 10 '" n_inf_nan_frac [9:0] $end
$var reg 1 0 n_is_inf $end
$var reg 1 / n_is_nan $end
$var reg 2 (" n_rm [1:0] $end
$var reg 1 - n_sign $end
$upscope $end
$upscope $end
$upscope $end
$enddefinitions $end
#0
$dumpvars
b0 ("
b0 '"
b0 &"
b0 %"
b0 $"
b0 #"
b0 ""
b0 !"
b0 ~
b0 }
b0 |
b0 {
b0 z
b11100000000 y
b0 x
b10100000000 w
b0 v
b10011 u
0t
b0 s
0r
0q
0p
b0 o
b0 n
b0 m
b0 l
b0 k
b0 j
b0 i
b0 h
b0 g
b0 f
b0 e
b0 d
b0 c
b0 b
b0 a
b0 `
b0 _
b0 ^
b1111 ]
0\
0[
b0 Z
b0 Y
b0 X
0W
0V
1U
0T
0S
1R
b0 Q
b10100000000 P
b1100000000 O
b11100000000 N
b10011 M
0L
0K
b100011100000000 J
0I
0H
b100010100000000 G
b100011100000000 F
b100010100000000 E
b10011 D
b0 C
0B
0A
b10100000000 @
0?
b11100000000 >
b0 =
b0 <
b0 ;
0:
09
b0 8
07
b0 6
05
b0 4
b0 3
b0 2
b0 1
00
0/
b0 .
0-
b0 ,
0+
b0 *
b100011100000000 )
z(
b100010100000000 '
0&
0%
1$
b100011100000000 #
b100010100000000 "
b0 !
$end
#10000
0$
#15000
1&
1%
#20000
b1000110000000000000000 <
b1000110000000000000000 Z
b1000110000000000000000 ""
b11100000000 4
b11100000000 X
b11100000000 ~
b10100000000 8
b10100000000 Y
b10100000000 |
z7
b10011 =
b10011 z
b10011 !"
1$
#30000
0$
#40000
b11000000000000 f
b1100000000000 e
b11000000000 d
b11000000000 c
b101000001100000 !
b101000001100000 ,
b101000001100000 _
b101000001100000 m
b1100000 n
b10100 l
b10100 g
b10001100000 b
b11 ]
b10100 j
b10001100000000 k
b100011000000000 i
b1000110000000000000000 2
b1000110000000000000000 h
b1000110000000000000000 &"
b10011 3
b10011 ^
b10011 %"
1$
#50000
0$
#60000
1$
#65000
b0 f
b0 e
b0 n
b0 d
b0 c
b0 b
b0 !
b0 ,
b0 _
b0 m
b0 l
b1111 ]
b0 k
b0 g
b0 i
b0 j
b0 4
b0 X
b0 ~
b0 <
b0 Z
b0 ""
b0 8
b0 Y
b0 |
07
b0 =
b0 z
b0 !"
b0 2
b0 h
b0 &"
b0 3
b0 ^
b0 %"
1?
0%
b10100000000 >
b10100000000 N
b10100000000 y
b11100000000 @
b11100000000 P
b11100000000 w
b10010 D
b10010 M
b10010 u
0&
b1100010100000000 J
b1100010100000000 #
b1100010100000000 )
b1100010100000000 F
b100001100000000 G
b100001100000000 "
b100001100000000 '
b100001100000000 E
#70000
0$
#80000
b1000110000000000000000 <
b1000110000000000000000 Z
b1000110000000000000000 ""
b10100000000 4
b10100000000 X
b10100000000 ~
b11100000000 8
b11100000000 Y
b11100000000 |
z7
b10010 =
b10010 z
b10010 !"
15
1&
1%
1$
#90000
0$
#100000
b11000000000000 f
b1100000000000 e
b11000000000 d
b11000000000 c
b1100000 n
b10011 l
b10011 g
b10001100000 b
b11 ]
b10011 j
b10001100000000 k
b100011000000000 i
b1100110001100000 !
b1100110001100000 ,
b1100110001100000 _
b1100110001100000 m
1t
b1000110000000000000000 2
b1000110000000000000000 h
b1000110000000000000000 &"
b10010 3
b10010 ^
b10010 %"
1-
1$
#110000
0$
#120000
1$
#130000
b0 f
b0 e
b0 n
b0 d
b0 c
b0 b
b0 l
b1111 ]
b0 k
b0 g
b0 i
b0 j
b0 !
b0 ,
b0 _
b0 m
0t
b0 4
b0 X
b0 ~
b0 <
b0 Z
b0 ""
b0 8
b0 Y
b0 |
07
b0 =
b0 z
b0 !"
05
b0 2
b0 h
b0 &"
b0 3
b0 ^
b0 %"
0-
0?
b1111111111 O
0%
b11111111111 >
b11111111111 N
b11111111111 y
b11111111111 @
b11111111111 P
b11111111111 w
b1101 D
b1101 M
b1101 u
0$
0&
b111101111111111 J
b111101111111111 #
b111101111111111 )
b111101111111111 F
b111101111111111 G
b111101111111111 "
b111101111111111 '
b111101111111111 E
#140000
1$
#145000
1&
1%
#150000
0$
#160000
b1111111111000000000001 <
b1111111111000000000001 Z
b1111111111000000000001 ""
b11111111111 4
b11111111111 X
b11111111111 ~
b11111111111 8
b11111111111 Y
b11111111111 |
z7
b1101 =
b1101 z
b1101 !"
1$
#170000
0$
#180000
b11111111100000 f
b11111111100000 e
b11111111100000 d
b11101111111110 !
b11101111111110 ,
b11101111111110 _
b11101111111110 m
b1111111110 n
b1110 l
b11111111100000 c
b1110 g
b11111111110 b
b0 ]
b1110 j
b11111111110000 k
b111111111100000 i
b1111111111000000000001 2
b1111111111000000000001 h
b1111111111000000000001 &"
b1101 3
b1101 ^
b1101 %"
1$
