lab6_birthGenerator/behavioral/procedural assignment/DDLab6_alwaysex_2018.v
module lab6(in, out); //模組 lab6(對應的輸入埠與輸出埠)
	
	//宣告區段
	input [2:0]in; //宣告輸入埠 in ,其形態為 3bit wire
	output  reg [3:0]out; //宣告輸出埠 out ,其形態為 4bit reg
	
	//邏輯區段
	always @(*) 
	//當 always 讀取的變數或線改變時，再次執行 always 內容
	begin //開始描述 always 內容 
		out[3] = (!in[2] & !in[1] & in[0]) | (in[2] & in[1] & in[0]); 
		//計算輸出埠 out 的第3個位數
		out[2] = (!in[2] & in[1]);
		out[1] = (!in[2] & in[1]) | (in[2] & !in[1] & in[0]);
		out[0] = (!in[2] & !in[1]) | (in[2] & in[0]) | (in[1] & !in[0]); 
	end //結束描述 always 內容 

endmodule //結束模組

lab6_birthGenerator/behavioral/procedural assignment/lab6_testbench.v
`timescale 1ns/1ps
module lab6_testbench;
reg [2:0] in;
wire [3:0] out;
integer i;
lab6 DUT(in,out);

initial begin
	$dumpfile("lab6.vcd");
	$dumpvars;
end

initial begin
    for(i=0;i<8;i=i+1) begin
       $monitor(out);
	   in=i;
	   #8;
    end
end
endmodule

lab6_birthGenerator/behavioral/procedural assignment/lab6.vcd
$date
	Thu Apr 19 21:51:09 2018
$end
$version
	Icarus Verilog
$end
$timescale
	1ps
$end
$scope module lab6_testbench $end
$var wire 4 ! out [3:0] $end
$var reg 3 " in [2:0] $end
$var integer 32 # i [31:0] $end
$scope module DUT $end
$var wire 3 $ in [2:0] $end
$var reg 4 % out [3:0] $end
$upscope $end
$upscope $end
$enddefinitions $end
#0
$dumpvars
b1 %
b0 $
b0 #
b0 "
b1 !
$end
#8000
b1001 !
b1001 %
b1 "
b1 $
b1 #
#16000
b10 "
b10 $
b10 #
#24000
b111 !
b111 %
b11 "
b11 $
b11 #
#32000
b0 !
b0 %
b100 "
b100 $
b100 #
#40000
b111 !
b111 %
b101 "
b101 $
b101 #
#48000
b10 !
b10 %
b110 "
b110 $
b110 #
#56000
b1000 !
b1000 %
b111 "
b111 $
b111 #
#64000
b1000 #
