lab9_16bit_ieeeFPAdder/FPAdder16bit/fp_norm.v
`timescale 1ns / 1ps

module fadd_norm (rm,is_nan,is_inf,inf_nan_frac,sign,temp_exp,cal_frac,s);
	//1 5 10
	//1 8 23
	input [14:0] cal_frac;
	input [9:0] inf_nan_frac;
	input [4:0] temp_exp;
	input [1:0] rm;
	input is_nan,is_inf;
	input sign;
	output [15:0] s;
	wire [13:0] f3,f2,f1,f0;
	//從左邊找到第一個1
	wire [3:0] zeros;
	assign zeros[3] = ~|cal_frac[13:6]; // 8-bit 0
	assign f3 = zeros[3]? {cal_frac[5:0],8'b0} : cal_frac[13:0];
	assign zeros[2] = ~|f3[13:10]; // 4-bit 0
	assign f2 = zeros[2]? {f3[9:0], 4'b0} : f3;
	assign zeros[1] = ~|f2[13:12]; // 2-bit 0
	assign f1 = zeros[1]? {f2[11:0], 2'b0} : f2;
	assign zeros[0] = ~f1[13]; // 1-bit 0
	assign f0 = zeros[0]? {f1[12:0], 1'b0} : f1;
	reg [13:0] frac0;
	reg [4:0] exp0;
	//位移以及修改exponent
	always @ * begin
		if (cal_frac[14]) begin
			frac0 = cal_frac[14:1]; // 1x.xxxxxxxxxxxxxxxxxxxxxxx xxx
			exp0 = temp_exp + 5'h1; // 1.xxxxxxxxxxxxxxxxxxxxxxx xxx
		end 
		else begin
			if ((temp_exp > zeros) && (f0[13])) begin // a normalized number
				exp0 = temp_exp - zeros;
				frac0 = f0; // 01.xxxxxxxxxxxxxxxxxxxxxxx xxx
			end
			else begin // is a denormalized number or 0
				exp0 = 0;
				if (temp_exp != 0) // (e - 127) = ((e - 1) - 126)
					frac0 = cal_frac[13:0] << (temp_exp - 5'h1);
				else frac0 = cal_frac[13:0];
			end
		end
	end
	//依照選取的模式執行round
	wire frac_plus_1 = // for rounding
	~rm[1] & ~rm[0] & frac0[2] & (frac0[1] | frac0[0]) |
	~rm[1] & ~rm[0] & frac0[2] & ~frac0[1] & ~frac0[0] & frac0[3] |
	~rm[1] & rm[0] & (frac0[2] | frac0[1] | frac0[0]) & sign |
	rm[1] & ~rm[0] & (frac0[2] | frac0[1] | frac0[0]) & ~sign;
	wire [11:0] frac_round = {1'b0,frac0[13:3]} + frac_plus_1;
	wire [4:0] exponent = frac_round[11]? exp0 + 5'h1 : exp0;
	wire overflow = &exp0 | &exponent;
	assign s = final_result(overflow, rm, sign, is_nan, is_inf, exponent, frac_round[9:0], inf_nan_frac);
	//處理例外狀況
	function [15:0] final_result;
		input overflow;
		input [1:0] rm;
		input sign, is_nan, is_inf;
		input [4:0] exponent;
		input [9:0] fraction, inf_nan_frac;
		casex ({overflow, rm, sign, is_nan, is_inf})
			6'b1_00_x_0_x : final_result = {sign,5'h1f,10'h0}; // inf
			6'b1_01_0_0_x : final_result = {sign,5'h1e,10'h3ff}; // max
			6'b1_01_1_0_x : final_result = {sign,5'h1f,10'h0}; // inf
			6'b1_10_0_0_x : final_result = {sign,5'h1f,10'h0}; // inf
			6'b1_10_1_0_x : final_result = {sign,5'h1e,10'h3ff}; // max
			6'b1_11_x_0_x : final_result = {sign,5'h1e,10'h3ff}; // max
			6'b0_xx_x_0_0 : final_result = {sign,exponent,fraction}; // nor
			6'bx_xx_x_1_x : final_result = {1'b1,5'h1f,inf_nan_frac}; // nan
			6'bx_xx_x_0_1 : final_result = {sign,5'h1f,inf_nan_frac}; // inf
			default : final_result = {sign,5'h0,10'h0}; // 0
		endcase
	endfunction
endmodule

lab9_16bit_ieeeFPAdder/FPAdder16bit/fp_reg_cal_norm.v
`timescale 1ns / 1ps
//////////////////////////////////////////////////////////////////////////////////
// Company: 
// Engineer: 
// 
// Create Date:    11:26:12 03/24/2017 
// Design Name: 
// Module Name:    float_adder 
// Project Name: 
// Target Devices: 
// Tool versions: 
// Description: 
//
// Dependencies: 
//
// Revision: 
// Revision 0.01 - File Created
// Additional Comments: 
//
//////////////////////////////////////////////////////////////////////////////////
module reg_cal_norm (c_rm,c_is_nan,c_is_inf,c_inf_nan_frac,c_sign,c_exp,
c_frac,clk,clrn,e,n_rm,n_is_nan,n_is_inf,
n_inf_nan_frac,n_sign,n_exp,n_frac); // pipeline regs
	input [14:0] c_frac;
	input [9:0] c_inf_nan_frac;
	input [4:0] c_exp;
	input [1:0] c_rm;
	input c_is_nan, c_is_inf, c_sign;
	input e; // e: enable
	input clk, clrn; // clock and reset
	output reg [14:0] n_frac;
	output reg [9:0] n_inf_nan_frac;
	output reg [4:0] n_exp;
	output reg [1:0] n_rm;
	output reg n_is_nan,n_is_inf,n_sign;
	always @ (posedge clk or negedge clrn) begin
		if (!clrn) begin
			n_rm <= 0;
			n_is_nan <= 0;
			n_is_inf <= 0;
			n_inf_nan_frac <= 0;
			n_sign <= 0;
			n_exp <= 0;
			n_frac <= 0;
		end else if (e) begin
			n_rm <= c_rm;
			n_is_nan <= c_is_nan;
			n_is_inf <= c_is_inf;
			n_inf_nan_frac <= c_inf_nan_frac;
			n_sign <= c_sign;
			n_exp <= c_exp;
			n_frac <= c_frac;
		end
	end
endmodule

lab9_16bit_ieeeFPAdder/FPAdder16bit/fp_cal.v
`timescale 1ns / 1ps

module fadd_cal (op_sub,large_frac24,small_frac27, cal_frac); // calculation
	//1 5 10
	input [10:0] large_frac24;
	input op_sub;
	input [13:0] small_frac27;
	output [14:0] cal_frac;
	//補上grs,以及避免溢位狀況,共28bit
	//23+3+1
	wire [14:0] aligned_large_frac = {1'b0,large_frac24,3'b000};
	wire [14:0] aligned_small_frac = {1'b0,small_frac27};
	//相減或相加
	assign cal_frac = op_sub?
	aligned_large_frac - aligned_small_frac :
	aligned_large_frac + aligned_small_frac;
endmodule

lab9_16bit_ieeeFPAdder/FPAdder16bit/fp_reg_align_cal.v
`timescale 1ns / 1ps
//////////////////////////////////////////////////////////////////////////////////
// Company: 
// Engineer: 
// 
// Create Date:    12:16:19 04/07/2017 
// Design Name: 
// Module Name:    float_control_2 
// Project Name: 
// Target Devices: 
// Tool versions: 
// Description: 
//
// Dependencies: 
//
// Revision: 
// Revision 0.01 - File Created
// Additional Comments: 
//
//////////////////////////////////////////////////////////////////////////////////
module reg_align_cal (a_rm,a_is_nan,a_is_inf,a_inf_nan_frac,a_sign,a_exp,
a_op_sub,a_large_frac,a_small_frac,clk,clrn,e,c_rm,
c_is_nan,c_is_inf,c_inf_nan_frac,c_sign,c_exp,
c_op_sub,c_large_frac,c_small_frac); // pipeline regs
	input [13:0] a_small_frac;
	input [10:0] a_large_frac;
	input [9:0] a_inf_nan_frac;
	input [4:0] a_exp;
	input [1:0] a_rm;
	input a_is_nan, a_is_inf, a_sign, a_op_sub;
	input e; // e: enable
	input clk, clrn; // clock and reset
	output reg [13:0] c_small_frac;
	output reg [10:0] c_large_frac;
	output reg [9:0] c_inf_nan_frac;
	output reg [4:0] c_exp;
	output reg [1:0] c_rm;
	output reg c_is_nan,c_is_inf,c_sign,c_op_sub;
	always @ (posedge clk or negedge clrn) begin
		if (!clrn) begin
			c_rm <= 0;
			c_is_nan <= 0;
			c_is_inf <= 0;
			c_inf_nan_frac <= 0;
			c_sign <= 0;
			c_exp <= 0;
			c_op_sub <= 0;
			c_large_frac <= 0;
			c_small_frac <= 0;
		end else if (e) begin
			c_rm <= a_rm;
			c_is_nan <= a_is_nan;
			c_is_inf <= a_is_inf;
			c_inf_nan_frac <= a_inf_nan_frac;
			c_sign <= a_sign;
			c_exp <= a_exp;
			c_op_sub <= a_op_sub;
			c_large_frac <= a_large_frac;
			c_small_frac <= a_small_frac;
		end
	end
endmodule

lab9_16bit_ieeeFPAdder/FPAdder16bit/fp_align.v
`timescale 1ns / 1ps

module fadd_align (a,b,sub,s_is_nan,s_is_inf,inf_nan_frac,sign,temp_exp,
op_sub,large_frac24,small_frac27); //alignment stage
	input [15:0] a,b;
	input sub;
	//1 8 23 
	//1 5 10 
	output [13:0] small_frac27;
	output [10:0] large_frac24;
	output [9:0] inf_nan_frac;
	output [4:0] temp_exp;
	output s_is_nan;
	output s_is_inf;
	output sign;
	output op_sub;
	//不看sign bit,判斷a or b大
	wire exchange = (b[14:0] > a[14:0]);
	wire [15:0] fp_large = exchange? b : a;
	wire [15:0] fp_small = exchange? a : b;
	//轉成1.f格式
	wire fp_large_hidden_bit = |fp_large[14:10];
	wire fp_small_hidden_bit = |fp_small[14:10];
	wire [10:0] large_frac24 = {fp_large_hidden_bit,fp_large[9:0]};
	wire [10:0] small_frac24 = {fp_small_hidden_bit,fp_small[9:0]};
	//儲存較大數的exponent
	assign temp_exp = fp_large[14:10];
	//判斷正負
	assign sign = exchange? sub^b[15] : a[15];
	//使用sub or add
	assign op_sub = sub ^ fp_large[15] ^ fp_small[15];
	//例外狀況
	wire fp_large_expo_is_ff = &fp_large[14:10]; // exp == 0xff
	wire fp_small_expo_is_ff = &fp_small[14:10];
	wire fp_large_frac_is_00 = ~|fp_large[9:0]; // frac == 0x0
	wire fp_small_frac_is_00 = ~|fp_small[9:0];
	wire fp_large_is_inf=fp_large_expo_is_ff & fp_large_frac_is_00;
	wire fp_small_is_inf=fp_small_expo_is_ff & fp_small_frac_is_00;
	wire fp_large_is_nan=fp_large_expo_is_ff & ~fp_large_frac_is_00;
	wire fp_small_is_nan=fp_small_expo_is_ff & ~fp_small_frac_is_00;
	assign s_is_inf = fp_large_is_inf | fp_small_is_inf;
	wire s_is_nan = fp_large_is_nan | fp_small_is_nan | ((sub ^ fp_small[15] ^ fp_large[15]) & fp_large_is_inf & fp_small_is_inf);
	wire [9:0] nan_frac = (a[8:0] > b[8:0])?	{1'b1,a[8:0]} : {1'b1,b[8:0]};
	assign inf_nan_frac = s_is_nan? nan_frac : 10'h0;
	//ea-eb
	wire [4:0] exp_diff = fp_large[14:10] - fp_small[14:10];
	wire small_den_only = (fp_large[14:10] != 0) & (fp_small[14:10] == 0);
	//計算需要位移幾位,並且位移
	wire [4:0] shift_amount = small_den_only? exp_diff - 5'h1 : exp_diff;
	wire [23:0] small_frac50 = (shift_amount >= 13)? {13'h0,small_frac24} : {small_frac24,13'h0} >> shift_amount;
	//留下11bit以及保護.循環位,計算多出來的位數,使用reduction OR簡化成1bit
	assign small_frac27 = {small_frac50[23:11],|small_frac50[10:0]};
endmodule

lab9_16bit_ieeeFPAdder/FPAdder16bit/fp_adder.v
`include "fp_align.v"
`include "fp_reg_align_cal.v"
`include "fp_cal.v"
`include "fp_norm.v"
`include "fp_reg_cal_norm.v"
`timescale 1ns / 1ps

module pipelined_fpadder (a,b,sub,rm,s,clk,clrn,e); // pipelined fp adder
	input clk, clrn; // clock and reset
	input [15:0] a, b; // fp a and b
	input [1:0] rm; // round mode
	input sub; // 1: sub; 0: add
	input e; // enable
	output [15:0] s; // fp output
	//1 5 10
	wire [13:0] a_small_frac;
	wire [10:0] a_large_frac;
	wire [9:0] a_inf_nan_frac;
	wire [4:0] a_exp;
	wire a_is_nan,a_is_inf;
	wire a_sign;
	wire a_op_sub;
	// exe1: alignment stage
	fadd_align alignment (a,b,sub,a_is_nan,a_is_inf,a_inf_nan_frac,a_sign,
	a_exp,a_op_sub,a_large_frac,a_small_frac);
	wire [13:0] c_small_frac;
	wire [10:0] c_large_frac;
	wire [9:0] c_inf_nan_frac;
	wire [4:0] c_exp;
	wire [1:0] c_rm;
	wire c_is_nan,c_is_inf;
	wire c_sign;
	wire c_op_sub;
	// pipelined registers
	reg_align_cal reg_ac (rm,a_is_nan,a_is_inf,a_inf_nan_frac,a_sign,a_exp,
	a_op_sub,a_large_frac,a_small_frac,clk,clrn,e,
	c_rm,c_is_nan,c_is_inf,c_inf_nan_frac,c_sign,
	c_exp,c_op_sub,c_large_frac,c_small_frac);
	wire [14:0] c_frac;
	// exe2: calculation stage
	fadd_cal calculation (c_op_sub,c_large_frac,c_small_frac,c_frac);
	wire [14:0] n_frac;
	wire [9:0] n_inf_nan_frac;
	wire [4:0] n_exp;
	wire [1:0] n_rm	;
	wire n_is_nan,n_is_inf;
	wire n_sign;
	// pipelined registers
	reg_cal_norm reg_cn (c_rm,c_is_nan,c_is_inf,c_inf_nan_frac,c_sign,c_exp,
	c_frac,clk,clrn,e,n_rm,n_is_nan,n_is_inf,
	n_inf_nan_frac,n_sign,n_exp,n_frac);
	// exe3: normalization stage
	fadd_norm normalization (n_rm,n_is_nan,n_is_inf,n_inf_nan_frac,n_sign,
	n_exp,n_frac,s);
endmodule

lab9_16bit_ieeeFPAdder/FPAdder16bit/testbench.v
`include "fp_adder.v"//
`timescale 1ns / 1ps

module test_bench;
reg clk; //clock
reg clrn; //è² ç·£??‚æ?…ç©º
reg[15:0] a;
reg[15:0] b;
reg en;
wire [15:0] result;
pipelined_fpadder test(a,b,1'b0,2'd0,result,clk,clrn,en);


initial #0 clk = 1'b1;
always #10 clk = ~clk;
  
initial begin
	a = 16'h4500;
	b = 16'h4700;
	en = 0;
	#0 clrn = 1'b0;
	#5 clrn = 1'b0;
	#10 clrn = 1'b1;
	en = 1'b1;
	#50
	/*if(result==16'h4A00)
		$display("----------Correct!----------");
	else
		//$display("----------Wrong!----------");
	//$display("Ans:%x, yours:%x\n",16'h4A00,result);
	*/
	a = 16'h4300;
	b = 16'hC500;
	en = 0;
	#0 clrn = 1'b0;
	#5 clrn = 1'b0;
	#10 clrn = 1'b1;
	en = 1'b1;
	#50
	if(result==16'hBE00)
		$display("----------Correct!----------");
	else
		$display("----------Wrong!----------");
	$display("Ans:%x, yours:%x\n",16'hBE00,result);
	a = 16'h7BFF;
	b = 16'h7BFF;
	en = 0;
	#0 clrn = 1'b0;
	#5 clrn = 1'b0;
	#10 clrn = 1'b1;
	en = 1'b1;
	#50
	$display("----------Exp!----------");
	$display("Ans:x, yours:%x\n",result);
	#500 $finish;
end

initial begin
	$dumpfile("fpadder.vcd");
	$dumpvars;
end

endmodule

lab9_16bit_ieeeFPAdder/FPAdder16bit/fpadder.vcd
$date
	Mon May 21 19:03:33 2018
$end
$version
	Icarus Verilog
$end
$timescale
	1ps
$end
$scope module test_bench $end
$var wire 16 ! result [15:0] $end
$var reg 16 " a [15:0] $end
$var reg 16 # b [15:0] $end
$var reg 1 $ clk $end
$var reg 1 % clrn $end
$var reg 1 & en $end
$scope module test $end
$var wire 16 ' a [15:0] $end
$var wire 16 ( b [15:0] $end
$var wire 1 $ clk $end
$var wire 1 % clrn $end
$var wire 1 & e $end
$var wire 2 ) rm [1:0] $end
$var wire 1 * sub $end
$var wire 16 + s [15:0] $end
$var wire 1 , n_sign $end
$var wire 2 - n_rm [1:0] $end
$var wire 1 . n_is_nan $end
$var wire 1 / n_is_inf $end
$var wire 10 0 n_inf_nan_frac [9:0] $end
$var wire 15 1 n_frac [14:0] $end
$var wire 5 2 n_exp [4:0] $end
$var wire 14 3 c_small_frac [13:0] $end
$var wire 1 4 c_sign $end
$var wire 2 5 c_rm [1:0] $end
$var wire 1 6 c_op_sub $end
$var wire 11 7 c_large_frac [10:0] $end
$var wire 1 8 c_is_nan $end
$var wire 1 9 c_is_inf $end
$var wire 10 : c_inf_nan_frac [9:0] $end
$var wire 15 ; c_frac [14:0] $end
$var wire 5 < c_exp [4:0] $end
$var wire 14 = a_small_frac [13:0] $end
$var wire 1 > a_sign $end
$var wire 1 ? a_op_sub $end
$var wire 11 @ a_large_frac [10:0] $end
$var wire 1 A a_is_nan $end
$var wire 1 B a_is_inf $end
$var wire 10 C a_inf_nan_frac [9:0] $end
$var wire 5 D a_exp [4:0] $end
$scope module alignment $end
$var wire 16 E a [15:0] $end
$var wire 16 F b [15:0] $end
$var wire 1 G fp_large_is_inf $end
$var wire 1 H fp_large_is_nan $end
$var wire 1 I fp_small_is_inf $end
$var wire 1 J fp_small_is_nan $end
$var wire 1 ? op_sub $end
$var wire 1 B s_is_inf $end
$var wire 1 A s_is_nan $end
$var wire 1 K small_den_only $end
$var wire 1 * sub $end
$var wire 5 L temp_exp [4:0] $end
$var wire 24 M small_frac50 [23:0] $end
$var wire 14 N small_frac27 [13:0] $end
$var wire 11 O small_frac24 [10:0] $end
$var wire 1 > sign $end
$var wire 5 P shift_amount [4:0] $end
$var wire 10 Q nan_frac [9:0] $end
$var wire 11 R large_frac24 [10:0] $end
$var wire 10 S inf_nan_frac [9:0] $end
$var wire 1 T fp_small_hidden_bit $end
$var wire 1 U fp_small_frac_is_00 $end
$var wire 1 V fp_small_expo_is_ff $end
$var wire 16 W fp_small [15:0] $end
$var wire 1 X fp_large_hidden_bit $end
$var wire 1 Y fp_large_frac_is_00 $end
$var wire 1 Z fp_large_expo_is_ff $end
$var wire 16 [ fp_large [15:0] $end
$var wire 5 \ exp_diff [4:0] $end
$var wire 1 ] exchange $end
$upscope $end
$scope module calculation $end
$var wire 14 ^ small_frac27 [13:0] $end
$var wire 1 6 op_sub $end
$var wire 11 _ large_frac24 [10:0] $end
$var wire 15 ` cal_frac [14:0] $end
$var wire 15 a aligned_small_frac [14:0] $end
$var wire 15 b aligned_large_frac [14:0] $end
$upscope $end
$scope module normalization $end
$var wire 1 c frac_plus_1 $end
$var wire 1 d overflow $end
$var wire 4 e zeros [3:0] $end
$var wire 5 f temp_exp [4:0] $end
$var wire 1 , sign $end
$var wire 16 g s [15:0] $end
$var wire 2 h rm [1:0] $end
$var wire 1 . is_nan $end
$var wire 1 / is_inf $end
$var wire 10 i inf_nan_frac [9:0] $end
$var wire 12 j frac_round [11:0] $end
$var wire 14 k f3 [13:0] $end
$var wire 14 l f2 [13:0] $end
$var wire 14 m f1 [13:0] $end
$var wire 14 n f0 [13:0] $end
$var wire 5 o exponent [4:0] $end
$var wire 15 p cal_frac [14:0] $end
$var reg 5 q exp0 [4:0] $end
$var reg 14 r frac0 [13:0] $end
$scope function final_result $end
$var reg 5 s exponent [4:0] $end
$var reg 16 t final_result [15:0] $end
$var reg 10 u fraction [9:0] $end
$var reg 10 v inf_nan_frac [9:0] $end
$var reg 1 w is_inf $end
$var reg 1 x is_nan $end
$var reg 1 y overflow $end
$var reg 2 z rm [1:0] $end
$var reg 1 { sign $end
$upscope $end
$upscope $end
$scope module reg_ac $end
$var wire 5 | a_exp [4:0] $end
$var wire 10 } a_inf_nan_frac [9:0] $end
$var wire 1 B a_is_inf $end
$var wire 1 A a_is_nan $end
$var wire 11 ~ a_large_frac [10:0] $end
$var wire 1 ? a_op_sub $end
$var wire 2 !" a_rm [1:0] $end
$var wire 1 > a_sign $end
$var wire 14 "" a_small_frac [13:0] $end
$var wire 1 $ clk $end
$var wire 1 % clrn $end
$var wire 1 & e $end
$var reg 5 #" c_exp [4:0] $end
$var reg 10 $" c_inf_nan_frac [9:0] $end
$var reg 1 9 c_is_inf $end
$var reg 1 8 c_is_nan $end
$var reg 11 %" c_large_frac [10:0] $end
$var reg 1 6 c_op_sub $end
$var reg 2 &" c_rm [1:0] $end
$var reg 1 4 c_sign $end
$var reg 14 '" c_small_frac [13:0] $end
$upscope $end
$scope module reg_cn $end
$var wire 5 (" c_exp [4:0] $end
$var wire 15 )" c_frac [14:0] $end
$var wire 10 *" c_inf_nan_frac [9:0] $end
$var wire 1 9 c_is_inf $end
$var wire 1 8 c_is_nan $end
$var wire 2 +" c_rm [1:0] $end
$var wire 1 4 c_sign $end
$var wire 1 $ clk $end
$var wire 1 % clrn $end
$var wire 1 & e $end
$var reg 5 ," n_exp [4:0] $end
$var reg 15 -" n_frac [14:0] $end
$var reg 10 ." n_inf_nan_frac [9:0] $end
$var reg 1 / n_is_inf $end
$var reg 1 . n_is_nan $end
$var reg 2 /" n_rm [1:0] $end
$var reg 1 , n_sign $end
$upscope $end
$upscope $end
$upscope $end
$enddefinitions $end
#0
$dumpvars
b0 /"
b0 ."
b0 -"
b0 ,"
b0 +"
b0 *"
b0 )"
b0 ("
b0 '"
b0 &"
b0 %"
b0 $"
b0 #"
b10100000000000 ""
b0 !"
b11100000000 ~
b0 }
b10001 |
0{
b0 z
0y
0x
0w
b0 v
b0 u
b0 t
b0 s
b0 r
b0 q
b0 p
b0 o
b0 n
b0 m
b0 l
b0 k
b0 j
b0 i
b0 h
b0 g
b0 f
b1111 e
0d
0c
b0 b
b0 a
b0 `
b0 _
b0 ^
1]
b0 \
b100011100000000 [
0Z
0Y
1X
b100010100000000 W
0V
0U
1T
b0 S
b11100000000 R
b1100000000 Q
b0 P
b10100000000 O
b10100000000000 N
b101000000000000000000000 M
b10001 L
0K
0J
0I
0H
0G
b100011100000000 F
b100010100000000 E
b10001 D
b0 C
0B
0A
b11100000000 @
0?
0>
b10100000000000 =
b0 <
b0 ;
b0 :
09
08
b0 7
06
b0 5
04
b0 3
b0 2
b0 1
b0 0
0/
0.
b0 -
0,
b0 +
0*
b0 )
b100011100000000 (
b100010100000000 '
0&
0%
1$
b100011100000000 #
b100010100000000 "
b0 !
$end
#10000
0$
#15000
1&
1%
#20000
b110000000000000 ;
b110000000000000 `
b110000000000000 )"
b10100000000000 a
b10100000000000 3
b10100000000000 ^
b10100000000000 '"
b11100000000000 b
b11100000000 7
b11100000000 _
b11100000000 %"
b10001 <
b10001 #"
b10001 ("
1$
#30000
0$
#40000
b10000000000000 n
b10000000000000 m
b10000000000000 l
b10000000000000 k
b100101000000000 !
b100101000000000 +
b100101000000000 g
b100101000000000 t
b1000000000 u
b10010 s
b10010 o
b11000000000 j
b0 e
b10010 q
b11000000000000 r
b110000000000000 1
b110000000000000 p
b110000000000000 -"
b10001 2
b10001 f
b10001 ,"
1$
#50000
0$
#60000
1$
#65000
b0 n
b0 m
b0 u
b0 l
b0 !
b0 +
b0 g
b0 t
b0 s
b0 k
b0 j
b0 o
b0 ;
b0 `
b0 )"
b1111 e
b0 r
b0 q
b0 a
b0 3
b0 ^
b0 '"
b0 b
b0 7
b0 _
b0 %"
b0 <
b0 #"
b0 ("
b0 1
b0 p
b0 -"
b0 2
b0 f
b0 ,"
1?
b1110000000000 =
b1110000000000 N
b1110000000000 ""
1>
b11100000000000000000000 M
b1 P
b10100000000 @
b10100000000 R
b10100000000 ~
b11100000000 O
b1 \
0%
b1100010100000000 [
b100001100000000 W
0&
b1100010100000000 #
b1100010100000000 (
b1100010100000000 F
b100001100000000 "
b100001100000000 '
b100001100000000 E
#70000
0$
#80000
b110000000000 ;
b110000000000 `
b110000000000 )"
b1110000000000 a
b1110000000000 3
b1110000000000 ^
b1110000000000 '"
b10100000000000 b
b10100000000 7
b10100000000 _
b10100000000 %"
16
b10001 <
b10001 #"
b10001 ("
14
1&
1%
1$
#90000
0$
#100000
b1000000000 u
b1111 s
b11000000000 j
b1111 o
b11000000000000 r
b1111 q
b11000000000000 n
b11000000000000 m
b110000000000 l
b110000000000 k
b10 e
b1011111000000000 !
b1011111000000000 +
b1011111000000000 g
b1011111000000000 t
1{
b110000000000 1
b110000000000 p
b110000000000 -"
b10001 2
b10001 f
b10001 ,"
1,
1$
#110000
0$
#120000
1$
#130000
b0 n
b0 m
b0 u
b0 l
b0 s
b0 k
b0 j
b0 o
b0 ;
b0 `
b0 )"
b1111 e
b0 r
b0 q
b0 !
b0 +
b0 g
b0 t
0{
b0 a
b0 3
b0 ^
b0 '"
b0 b
b0 7
b0 _
b0 %"
06
b0 <
b0 #"
b0 ("
04
b0 1
b0 p
b0 -"
b0 2
b0 f
b0 ,"
0,
0?
b11111111111000 =
b11111111111000 N
b11111111111000 ""
b111111111110000000000000 M
b0 P
b11111111111 @
b11111111111 R
b11111111111 ~
b11110 D
b11110 L
b11110 |
0>
b11111111111 O
b0 \
b1111111111 Q
0%
b111101111111111 [
0]
b111101111111111 W
0$
0&
b111101111111111 #
b111101111111111 (
b111101111111111 F
b111101111111111 "
b111101111111111 '
b111101111111111 E
#140000
1$
#145000
1&
1%
#150000
0$
#160000
b111111111110000 ;
b111111111110000 `
b111111111110000 )"
b11111111111000 a
b11111111111000 3
b11111111111000 ^
b11111111111000 '"
b11111111111000 b
b11111111111 7
b11111111111 _
b11111111111 %"
b11110 <
b11110 #"
b11110 ("
1$
#170000
0$
#180000
b11111111110000 n
b11111111110000 m
b11111111110000 l
b111110000000000 !
b111110000000000 +
b111110000000000 g
b111110000000000 t
b1111111111 u
b11111 s
1y
b11111111110000 k
b11111 o
1d
b11111111111 j
b0 e
b11111 q
b11111111111000 r
b111111111110000 1
b111111111110000 p
b111111111110000 -"
b11110 2
b11110 f
b11110 ,"
1$
