lab11_32bit_Multiplier/part5/32mpy.v
`timescale 1ns/1ps
module lab(CLK, RST, in_a, in_b, Product, Product_Valid);
input CLK, RST;
input signed [31:0]	in_a;	// Multiplicand
input signed [31:0]	in_b;// Multiplier
output reg signed [63:0] Product;
output reg Product_Valid;

reg signed [31:0] Mplicand;
reg signed [32:0] Mplier;
reg [4:0] Counter;
reg	sign;

//Counter
always @(posedge CLK or posedge RST)
begin
	if(RST)
		Counter <=5'b0;
	else
		Counter <= Counter +5'b1;
end

//Multiplier
always @(posedge CLK or posedge RST)
begin
	//初始化數值
	if(RST) begin
		Product  <= 64'b0;
		Mplicand <= 32'b0;
		Mplier   <= 33'b0;	
	end 
	
	//輸入乘數與被乘數
	else if(Counter == 5'd0) begin
		Mplicand <= in_a;
		Mplier <= {in_b,1'b0};
	end 
	
	else if(in_b ==1 ) begin
		Product=in_a;
	end
	
	//乘法與數值移位
	/* write down your design below */
	else if(Counter <=5'd11) 
	begin
		if((Mplier[2]==1'b0 & Mplier[1]==1'b0 & Mplier[0]==1'b1) | (Mplier[2]==1'b0 & Mplier[1]==1'b1 & Mplier[0]==1'b0)) //001 010 +A
			Product <= Mplicand + Product;
		else if(Mplier[2]==1'b0 & Mplier[1] == 1'b1 & Mplier[0] == 1'b1 ) //+2A
			Product <= Product + (Mplicand * 2 );
		else if(Mplier[2]==1'b1 & Mplier[1] == 1'b0 & Mplier[0] == 1'b0) //-2A
			Product <= Product - (Mplicand * 2 );
		else if((Mplier[2]==1'b1 & Mplier[1]==1'b0 & Mplier[0]==1'b1) | (Mplier[2]==1'b1 & Mplier[1]==1'b1 & Mplier[0]==1'b0)) //101 110 -A
			Product <= Product - Mplicand;
		//$display("%d,%d",Product,Mplicand);
		Mplier <= Mplier >> 2'b10;
		Mplicand <= Mplicand << 2'b10;
	end 

	/* write down your design upon */
end

//判斷輸出
always @(posedge CLK or posedge RST)
begin
	if(RST)
		Product_Valid <=1'b0;
	else if(Counter==5'd11)
		Product_Valid <=1'b1;
	else
		Product_Valid <=1'b0;
end

endmodule

lab11_32bit_Multiplier/part5/tb32mpy.v
`timescale 1ns/1ps
`include "32mpy.v"

module tb_lab();
reg [31:0] in_a;
reg [31:0] in_b;
reg CLK;
reg reset;
wire signed [63:0] out;
wire out_valid;

reg [5:0]	count;
reg signed [64:0]	correct_ans;
reg error;
reg signed [63:0]	 temp_a;
reg signed [63:0]	temp_b;

lab m1(CLK, reset, in_a, in_b, out, out_valid);

initial begin
	$dumpfile("lab11.vcd");  //gtkwave
	$dumpvars;
	CLK = 1'b0;
	
	#10 reset = 1;//正數*正數
	temp_a = 32'd30;
	temp_b = 32'd90;
	#20 reset = 0;
	
	#260 reset = 1;//正數*負數
	temp_a = 32'd30;
	temp_b = -32'd90;
	#20 reset = 0;
	
	#260 reset = 1;//負數*正數
	temp_a = -32'd30;
	temp_b = 32'd90;
	#20 reset = 0;
	
	#260 reset = 1;//負數*負數
	temp_a = -32'd30;
	temp_b = 32'd1;
	#20 reset = 0;

	#260 $finish;
end

always #10 CLK = ~CLK;

always @(posedge CLK or posedge reset)
begin
	if(reset)//初始化
	begin
		count <= 0;
		in_a <= temp_a;
		in_b <= temp_b;
		correct_ans <= 0;
		error <= 0;
	end

	else//對答案
	begin
		correct_ans <= temp_a *temp_b;
		count <= count +1;

		if(out_valid==1)
			if(out != correct_ans)
			begin
				error <=1;
				$display ();
				$display ("// Fail //");
				$display ("//%d * %d = ?",temp_a, temp_b);
				$display ("//your answer is %d, but correct answer is %d\n",
				out, correct_ans);
			end
			
			else
			begin
				error <= 0;
				$display ();
				$display ("// Successful //");
				$display ("//%d * %d = ?",temp_a, temp_b);
				$display ("//your answer is %d,  correct answer is %d\n",
				out, correct_ans);
			end
	end
end

endmodule

lab11_32bit_Multiplier/part5/lab11.vcd
$date
	Mon May 28 20:51:46 2018
$end
$version
	Icarus Verilog
$end
$timescale
	1ps
$end
$scope module tb_lab $end
$var wire 1 ! out_valid $end
$var wire 64 " out [63:0] $end
$var reg 1 # CLK $end
$var reg 65 $ correct_ans [64:0] $end
$var reg 6 % count [5:0] $end
$var reg 1 & error $end
$var reg 32 ' in_a [31:0] $end
$var reg 32 ( in_b [31:0] $end
$var reg 1 ) reset $end
$var reg 64 * temp_a [63:0] $end
$var reg 64 + temp_b [63:0] $end
$scope module m1 $end
$var wire 1 # CLK $end
$var wire 1 ) RST $end
$var wire 32 , in_a [31:0] $end
$var wire 32 - in_b [31:0] $end
$var reg 5 . Counter [4:0] $end
$var reg 32 / Mplicand [31:0] $end
$var reg 33 0 Mplier [32:0] $end
$var reg 64 1 Product [63:0] $end
$var reg 1 ! Product_Valid $end
$upscope $end
$upscope $end
$enddefinitions $end
#0
$dumpvars
bx 1
bx 0
bx /
bx .
bx -
bx ,
bx +
bx *
x)
bx (
bx '
x&
bx %
bx $
0#
bx "
x!
$end
#10000
b0 .
b0 0
b0 /
b0 "
b0 1
0!
0&
b0 $
b1011010 (
b1011010 -
b11110 '
b11110 ,
b0 %
1#
b1011010 +
b11110 *
1)
#20000
0#
#30000
b1 %
b101010001100 $
b10110100 0
b11110 /
b1 .
1#
0)
#40000
0#
#50000
b10 .
b1111000 /
b101101 0
b1111111111111111111111111111111111111111111111111111111111000100 "
b1111111111111111111111111111111111111111111111111111111111000100 1
b10 %
1#
#60000
0#
#70000
b11 %
b111100000 /
b1011 0
b1111111111111111111111111111111111111111111111111111111101001100 "
b1111111111111111111111111111111111111111111111111111111101001100 1
b11 .
1#
#80000
0#
#90000
b100 .
b11110000000 /
b10 0
b1100001100 "
b1100001100 1
b100 %
1#
#100000
0#
#110000
b101 %
b1111000000000 /
b0 0
b101010001100 "
b101010001100 1
b101 .
1#
#120000
0#
#130000
b110 .
b111100000000000 /
b110 %
1#
#140000
0#
#150000
b111 %
b11110000000000000 /
b111 .
1#
#160000
0#
#170000
b1000 .
b1111000000000000000 /
b1000 %
1#
#180000
0#
#190000
b1001 %
b111100000000000000000 /
b1001 .
1#
#200000
0#
#210000
b1010 .
b11110000000000000000000 /
b1010 %
1#
#220000
0#
#230000
b1011 %
b1111000000000000000000000 /
b1011 .
1#
#240000
0#
#250000
b1100 .
b111100000000000000000000000 /
1!
b1100 %
1#
#260000
0#
#270000
b1101 %
0!
b1101 .
1#
#280000
0#
#290000
b0 .
b0 /
b0 "
b0 1
b0 $
b11111111111111111111111110100110 (
b11111111111111111111111110100110 -
b0 %
1#
b1111111111111111111111111111111111111111111111111111111110100110 +
1)
#300000
0#
#310000
b1 %
b11111111111111111111111111111111111111111111111111111010101110100 $
b111111111111111111111111101001100 0
b11110 /
b1 .
1#
0)
#320000
0#
#330000
b10 .
b1111000 /
b1111111111111111111111111010011 0
b1111111111111111111111111111111111111111111111111111111111000100 "
b1111111111111111111111111111111111111111111111111111111111000100 1
b10 %
1#
#340000
0#
#350000
b11 %
b111100000 /
b11111111111111111111111110100 0
b10110100 "
b10110100 1
b11 .
1#
#360000
0#
#370000
b100 .
b11110000000 /
b111111111111111111111111101 0
b1111111111111111111111111111111111111111111111111111110011110100 "
b1111111111111111111111111111111111111111111111111111110011110100 1
b100 %
1#
#380000
0#
#390000
b101 %
b1111000000000 /
b1111111111111111111111111 0
b1111111111111111111111111111111111111111111111111111010101110100 "
b1111111111111111111111111111111111111111111111111111010101110100 1
b101 .
1#
#400000
0#
#410000
b110 .
b111100000000000 /
b11111111111111111111111 0
b110 %
1#
#420000
0#
#430000
b111 %
b11110000000000000 /
b111111111111111111111 0
b111 .
1#
#440000
0#
#450000
b1000 .
b1111000000000000000 /
b1111111111111111111 0
b1000 %
1#
#460000
0#
#470000
b1001 %
b111100000000000000000 /
b11111111111111111 0
b1001 .
1#
#480000
0#
#490000
b1010 .
b11110000000000000000000 /
b111111111111111 0
b1010 %
1#
#500000
0#
#510000
b1011 %
b1111000000000000000000000 /
b1111111111111 0
b1011 .
1#
#520000
0#
#530000
b1100 .
b111100000000000000000000000 /
b11111111111 0
1!
b1100 %
1#
#540000
0#
#550000
b1101 %
0!
b1101 .
1#
#560000
0#
#570000
b0 .
b0 0
b0 /
b0 "
b0 1
b0 $
b1011010 (
b1011010 -
b11111111111111111111111111100010 '
b11111111111111111111111111100010 ,
b0 %
1#
b1011010 +
b1111111111111111111111111111111111111111111111111111111111100010 *
1)
#580000
0#
#590000
b1 %
b11111111111111111111111111111111111111111111111111111010101110100 $
b10110100 0
b11111111111111111111111111100010 /
b1 .
1#
0)
#600000
0#
#610000
b10 .
b11111111111111111111111110001000 /
b101101 0
b111100 "
b111100 1
b10 %
1#
#620000
0#
#630000
b11 %
b11111111111111111111111000100000 /
b1011 0
b10110100 "
b10110100 1
b11 .
1#
#640000
0#
#650000
b100 .
b11111111111111111111100010000000 /
b10 0
b1111111111111111111111111111111111111111111111111111110011110100 "
b1111111111111111111111111111111111111111111111111111110011110100 1
b100 %
1#
#660000
0#
#670000
b101 %
b11111111111111111110001000000000 /
b0 0
b1111111111111111111111111111111111111111111111111111010101110100 "
b1111111111111111111111111111111111111111111111111111010101110100 1
b101 .
1#
#680000
0#
#690000
b110 .
b11111111111111111000100000000000 /
b110 %
1#
#700000
0#
#710000
b111 %
b11111111111111100010000000000000 /
b111 .
1#
#720000
0#
#730000
b1000 .
b11111111111110001000000000000000 /
b1000 %
1#
#740000
0#
#750000
b1001 %
b11111111111000100000000000000000 /
b1001 .
1#
#760000
0#
#770000
b1010 .
b11111111100010000000000000000000 /
b1010 %
1#
#780000
0#
#790000
b1011 %
b11111110001000000000000000000000 /
b1011 .
1#
#800000
0#
#810000
b1100 .
b11111000100000000000000000000000 /
1!
b1100 %
1#
#820000
0#
#830000
b1101 %
0!
b1101 .
1#
#840000
0#
#850000
b0 .
b0 /
b0 "
b0 1
b0 $
b1 (
b1 -
b0 %
1#
b1 +
1)
#860000
0#
#870000
b1 %
b11111111111111111111111111111111111111111111111111111111111100010 $
b10 0
b11111111111111111111111111100010 /
b1 .
1#
0)
#880000
0#
#890000
b10 .
b10 %
b1111111111111111111111111111111111111111111111111111111111100010 "
b1111111111111111111111111111111111111111111111111111111111100010 1
1#
#900000
0#
#910000
b11 %
b11 .
1#
#920000
0#
#930000
b100 .
b100 %
1#
#940000
0#
#950000
b101 %
b101 .
1#
#960000
0#
#970000
b110 .
b110 %
1#
#980000
0#
#990000
b111 %
b111 .
1#
#1000000
0#
#1010000
b1000 .
b1000 %
1#
#1020000
0#
#1030000
b1001 %
b1001 .
1#
#1040000
0#
#1050000
b1010 .
b1010 %
1#
#1060000
0#
#1070000
b1011 %
b1011 .
1#
#1080000
0#
#1090000
b1100 .
1!
b1100 %
1#
#1100000
0#
#1110000
b1101 %
0!
b1101 .
1#
#1120000
0#
#1130000
b1110 .
b1110 %
1#
